{"Selection":{
	"button" : "{{ Series }} &middot; {{ Pitch }}<br>{{ Capacitance }} &middot; {{ Rated_Voltage }}<br>{{ Size_Length }}&middot;{{ Size_Width }}&middot;{{ Size_Height }}"
},"Filter":{},"Settings":{},"Version":"0.11","Properties":[{"PropertyName":"Capacitance","Title":"Capacitance","Type":"Undefined","Shortcut":"C","Base":1.0,"Format":"{0:n}","UnitSystemID":13,"ClassTitle":"Basic","ClassOrder":1,"Settings":{}},{"PropertyName":"Capacitance_Change_TC","Title":"Capacitance Change in TC by Frequency","Type":"Undefined","Shortcut":"dC","Base":0.01,"Format":"{0:n}","UnitSystemID":7,"ClassTitle":"Basic","ClassOrder":1,"Settings":{}},{"PropertyName":"Capacitance_nFTC","Title":"Capacitance TC","Type":"Undefined","Shortcut":"Cntc","Base":1E-09,"Format":"{0:n}","UnitSystemID":13,"ClassTitle":"Basic","ClassOrder":1,"Settings":{}},{"PropertyName":"Series","Title":"Component Series","Type":"Undefined","Shortcut":"series","Base":1.0,"Format":"{0:n}","UnitSystemID":2,"ClassTitle":"Basic","ClassOrder":1,"Settings":{"filter":{"template": "multiselect","source": true} }},{"PropertyName":"CQC","Title":"CQC Certificate File Name","Type":"Undefined","Shortcut":"cqc","Base":1.0,"Format":"{0:n}","UnitSystemID":35,"ClassTitle":"Basic","ClassOrder":1,"Settings":{}},{"PropertyName":"Datasheet","Title":"Datasheet","Type":"Undefined","Shortcut":"ds","Base":1.0,"Format":"{0:n}","UnitSystemID":1,"ClassTitle":"Basic","ClassOrder":1,"Settings":{}},{"PropertyName":"DF100","Title":"Disipation Factor 100kHz","Type":"Undefined","Shortcut":"df100","Base":1.0,"Format":"{0:n}","UnitSystemID":7,"ClassTitle":"Basic","ClassOrder":1,"Settings":{}},{"PropertyName":"DF10","Title":"Disipation Factor 10kHz","Type":"Undefined","Shortcut":"df10","Base":1.0,"Format":"{0:n}","UnitSystemID":7,"ClassTitle":"Basic","ClassOrder":1,"Settings":{}},{"PropertyName":"DF1","Title":"Disipation Factor 1kHz","Type":"Undefined","Shortcut":"df1","Base":1.0,"Format":"{0:n}","UnitSystemID":7,"ClassTitle":"Basic","ClassOrder":1,"Settings":{}},{"PropertyName":"DF_Frequency_TC","Title":"Disipation Factor in TC by Frequency","Type":"Undefined","Shortcut":"dfFTC","Base":0.01,"Format":"{0:n}","UnitSystemID":7,"ClassTitle":"Basic","ClassOrder":1,"Settings":{}},{"PropertyName":"DF_Temperature_TC","Title":"Disipation Factor in TC by Temperature","Type":"Undefined","Shortcut":"dfTTC","Base":0.01,"Format":"{0:n}","UnitSystemID":7,"ClassTitle":"Basic","ClassOrder":1,"Settings":{}},{"PropertyName":"dVdt","Title":"dV / dt","Type":"Undefined","Shortcut":"dvdt","Base":1.0,"Format":"{0:n}","UnitSystemID":32,"ClassTitle":"Basic","ClassOrder":1,"Settings":{}},{"PropertyName":"Frequency_kHz","Title":"Frequency (kHz)","Type":"Undefined","Shortcut":"FkHz","Base":1000.0,"Format":"{0:n}","UnitSystemID":5,"ClassTitle":"Basic","ClassOrder":1,"Settings":{}},{"PropertyName":"Frequency_Mhz","Title":"Frequency (Mhz)","Type":"Undefined","Shortcut":"FMhz","Base":1000000.0,"Format":"{0:n}","UnitSystemID":5,"ClassTitle":"Basic","ClassOrder":1,"Settings":{}},{"PropertyName":"Size_Height","Title":"Height","Type":"IsMax","Shortcut":"height","Base":1.0,"Format":"{0:n}","UnitSystemID":3,"ClassTitle":"Basic","ClassOrder":1,"Settings":{}},{"PropertyName":"Impedance_TC","Title":"Impedance TC","Type":"Undefined","Shortcut":"Ztc","Base":1.0,"Format":"{0:n}","UnitSystemID":11,"ClassTitle":"Basic","ClassOrder":1,"Settings":{}},{"PropertyName":"Resistance_Iso","Title":"Isolation Resistance","Type":"Undefined","Shortcut":"Riso","Base":1.0,"Format":"{0:n}","UnitSystemID":10,"ClassTitle":"Basic","ClassOrder":1,"Settings":{}},{"PropertyName":"Size_Length","Title":"Length","Type":"IsMax","Shortcut":"length","Base":1.0,"Format":"{0:n}","UnitSystemID":3,"ClassTitle":"Basic","ClassOrder":1,"Settings":{}},{"PropertyName":"Order_Code","Title":"Order Code","Type":"Undefined","Shortcut":"code","Base":1.0,"Format":"{0:n}","UnitSystemID":1,"ClassTitle":"Basic","ClassOrder":1,"Settings":{"filter":{"template":"multivalue","operator":"contains"}}},{"PropertyName":"Part_Description","Title":"Part Description","Type":"Undefined","Shortcut":"desc","Base":1.0,"Format":"{0:n}","UnitSystemID":1,"ClassTitle":"Basic","ClassOrder":1,"Settings":{}},{"PropertyName":"Pitch","Title":"Pitch","Type":"Undefined","Shortcut":"pitch","Base":1.0,"Format":"{0:n}","UnitSystemID":3,"ClassTitle":"Basic","ClassOrder":1,"Settings":{"filter":{"template": "rangeslider2"} }},{"PropertyName":"Rated_Voltage","Title":"Rated Voltage","Type":"Undefined","Shortcut":"V","Base":1.0,"Format":"{0:n}","UnitSystemID":9,"ClassTitle":"Basic","ClassOrder":1,"Settings":{}},{"PropertyName":"Current_RMS","Title":"Ripple current","Type":"Undefined","Shortcut":"Irms","Base":1.0,"Format":"{0:n}","UnitSystemID":8,"ClassTitle":"Basic","ClassOrder":1,"Settings":{}},{"PropertyName":"Voltage_RMS","Title":"RMS Voltage","Type":"Undefined","Shortcut":"Vrms","Base":1.0,"Format":"{0:n}","UnitSystemID":9,"ClassTitle":"Basic","ClassOrder":1,"Settings":{}},{"PropertyName":"ULCADTNV","Title":"TNV/SELV isolation capacitors_CAD\r\n","Type":"Undefined","Shortcut":"ulcadtnv","Base":1.0,"Format":"{0:n}","UnitSystemID":35,"ClassTitle":"Basic","ClassOrder":1,"Settings":{}},{"PropertyName":"ULUSTNV","Title":"TNV/SELV isolation capacitors_US\r\n","Type":"Undefined","Shortcut":"ulustnv","Base":1.0,"Format":"{0:n}","UnitSystemID":35,"ClassTitle":"Basic","ClassOrder":1,"Settings":{}},{"PropertyName":"Is_Internal","Title":"True, If product is only visible internally","Type":"Undefined","Shortcut":"internal","Base":1.0,"Format":"{0:n}","UnitSystemID":21,"ClassTitle":"Basic","ClassOrder":1,"Settings":{}},{"PropertyName":"Type","Title":"Type","Type":"Undefined","Shortcut":"type","Base":1.0,"Format":"{0:n}","UnitSystemID":2,"ClassTitle":"Basic","ClassOrder":1,"Settings":{}},{"PropertyName":"ULCAD","Title":"UL-CAD Certificate File Name","Type":"Undefined","Shortcut":"ulcad","Base":1.0,"Format":"{0:n}","UnitSystemID":35,"ClassTitle":"Basic","ClassOrder":1,"Settings":{}},{"PropertyName":"ULUS","Title":"UL-US Certificate File Name","Type":"Undefined","Shortcut":"ulus","Base":1.0,"Format":"{0:n}","UnitSystemID":35,"ClassTitle":"Basic","ClassOrder":1,"Settings":{}},{"PropertyName":"VDE","Title":"VDE Certificate File Name","Type":"Undefined","Shortcut":"vde","Base":1.0,"Format":"{0:n}","UnitSystemID":35,"ClassTitle":"Basic","ClassOrder":1,"Settings":{}},{"PropertyName":"Size_Width","Title":"Width","Type":"IsMax","Shortcut":"width","Base":1.0,"Format":"{0:n}","UnitSystemID":3,"ClassTitle":"Basic","ClassOrder":1,"Settings":{"filter":{"template": "rangeslider"} }},{"PropertyName":"Assembling_Technology","Title":"Assembling Technology","Type":"Undefined","Shortcut":"ast","Base":1.0,"Format":"{0:n}","UnitSystemID":2,"ClassTitle":"Mounting","ClassOrder":2,"Settings":{}},{"PropertyName":"Temperature_MIN","Title":"Minimum Operating Temperature","Type":"Undefined","Shortcut":"Tmin","Base":1.0,"Format":"{0:n}","UnitSystemID":4,"ClassTitle":"Enviromental","ClassOrder":4,"Settings":{}},{"PropertyName":"Temperature","Title":"Operating Temperature","Type":"Undefined","Shortcut":"T","Base":1.0,"Format":"{0:n}","UnitSystemID":4,"ClassTitle":"Enviromental","ClassOrder":4,"Settings":{}},{"PropertyName":"Temperature_OPT","Title":"Optimal Temperature","Type":"Undefined","Shortcut":"Topt","Base":1.0,"Format":"{0:n}","UnitSystemID":4,"ClassTitle":"Enviromental","ClassOrder":4,"Settings":{}}],"GridColumns":[{"field":"Order_Code","FieldUnitSystemID":1,"Settings":{"title":"Order Code", "supertitle": "General", "filter": {"template": "multivalue", "operator":"contains", "rule":"noSpaces"}, "width": "135px", "headerAttributes":{"title":"Order-Code"} }},{"field":"Series","FieldUnitSystemID":2,"Settings":{"title":"Series", "supertitle": "General", "filter":{"template":"multiselect","source":true},"width":9,"headerAttributes":{"title":"Product-Series"}}},{"field":"Datasheet","FieldUnitSystemID":1,"Settings":{"title": "Spec", "supertitle":"General", "filterable": false, "sortable": false, "Source": "Order_Code", "format":"<a href=\"https://katalog.we-online.com/spec/{0}\" target=\"_blank\"><div class=\"grid-column-img pdf-icon\"/></a>","class":"align-center", "width": "40px", "headerAttributes":{"title":"Datasheet"} } },{"field":"Type","FieldUnitSystemID":2,"Settings":{"title":"Type",  "supertitle":"General", "width":"75px", "filter":{"template": "multiselect","source": true}, "headerAttributes":{"title":"Type"} }},{"field":"Part_Description","FieldUnitSystemID":1,"Settings":{"title":"Description", "supertitle": "General", "width":"190px", "filter":{"template":"multiselect","source":true},"headerAttributes":{"title":"Description"}}},{"field":"Capacitance","FieldUnitSystemID":13,"Settings":{"unit":{"id":13,"factor":0}, "width":"70px", "filter":{"defaultBase": 0.000000001, "units": "1E-09,1E-06"},"title":"C", "supertitle":"Electrical Properties", "class":"align-right", "headerAttributes":{"title":"Capacitance"} }},{"field":"Rated_Voltage","FieldUnitSystemID":9,"Settings":{"unit":{"id":9,"factor":0}, "width":"60px", "title":"V<sub>R</sub>","supertitle":"Electrical Properties", "class":"align-right", "headerAttributes":{"title":"Rated Voltage"} }},{"field":"DF1","FieldUnitSystemID":7,"Settings":{"unit":{"id":7,"factor":0.01}, "title":"DF @ 1 kHz", "width":"110px", "format":"< {0}","supertitle":"Electrical Properties", "filter":{"defaultBase":0.01,"units": "0.01"}, "precision": 2, "class":"align-right", "headerAttributes":{"title":"Dissipation Factor at 1 kHz"} }},{"field":"DF10","FieldUnitSystemID":7,"Settings":{"unit":{"id":7,"factor":0.01}, "width":"120px", "title":"DF @ 10 kHz", "format":"< {0}","supertitle":"Electrical Properties", "filter":{"defaultBase":0.01,"units": "0.01"}, "precision": 2, "class":"align-right", "headerAttributes":{"title":"Dissipation Factor at 10 kHz"} }},{"field":"DF100","FieldUnitSystemID":7,"Settings":{"unit":{"id":7,"factor":0.01}, "width":"125px", "title":"DF @ 100 kHz", "format":"< {0}","supertitle":"Electrical Properties", "filter":{"defaultBase":0.01,"units": "0.01"}, "precision": 2, "class":"align-right", "headerAttributes":{"title":"Dissipation Factor at 100 kHz"} }},{"field":"Impedance_TC","FieldUnitSystemID":11,"Settings":{"unit":{"id":11,"factor":0}, "TCPanel":{"id":16, "titleTemplate":"Z@{{ label }}"}, "title":"Z@", "supertitle":"Electrical Properties", "class":"align-right calculated", "width": "105px", "listed":false, "hidden": true, "headerAttributes":{"title":"Impedance"} }},{"field":"Capacitance_Change_TC","FieldUnitSystemID":7,"FieldUnitBase":0.01,"Settings":{"unit":{"id":7,"factor":0}, "TCPanel":{"id":58, "titleTemplate":"ΔC@{{ label }}", "negatives": true}, "title":"ΔC@", "supertitle":"Electrical Properties", "class":"align-right calculated", "width": "115px", "listed":false, "hidden": true, "filter":{"defaultBase":0.01,"units": "0.01"}, "precision": 4, "headerAttributes":{"title":"Capacitance Change"}, "templateCheckNumber": true }},{"field":"DF_Frequency_TC","FieldUnitSystemID":7,"FieldUnitBase":0.01,"Settings":{"unit":{"id":7,"factor":0}, "TCPanel":{"id":17, "titleTemplate":"DF<sub>F</sub> @{{ label }}"}, "title":"DF<sub>F</sub>@", "supertitle":"Electrical Properties", "class":"align-right calculated", "width": "125px", "listed":false, "hidden": true, "filter":{"defaultBase":0.01,"units": "0.01"}, "headerAttributes":{"title":"Dissipation Factor"} }},{"field":"Capacitance_nFTC","FieldUnitSystemID":13,"FieldUnitBase":1E-09,"Settings":{"unit":{"id":13,"factor":0}, "TCPanel":{"id":18, "titleTemplate":"C@{{ label }}"}, "title":"C @", "supertitle":"Electrical Properties", "class":"align-right calculated", "width": "100px", "listed":false, "hidden": true, "headerAttributes":{"title":"Capacitance"} }},{"field":"DF_Temperature_TC","FieldUnitSystemID":7,"FieldUnitBase":0.01,"Settings":{"unit":{"id":7,"factor":0}, "TCPanel":{"id":59, "titleTemplate":"DF<sub>T</sub>@{{ label }}"}, "title":"DF<sub>T</sub>@", "supertitle":"Electrical Properties", "class":"align-right calculated", "width": "110px", "listed":false, "hidden": true, "filter":{"defaultBase":0.01,"units": "0.01"}, "headerAttributes":{"title":"Dissipation Factor"} }},{"field":"Voltage_RMS","FieldUnitSystemID":9,"Settings":{"unit":{"id":9,"factor":0},"TCPanel":{"id":150,"titleTemplate":"V<sub>RMS</sub>@{{ label }}"},"title":"Vrms @","supertitle":"Electrical Properties","class":"align-right calculated","width":"140px","listed":false, "hidden":true,"headerAttributes":{"title":"V<sub>RMS</sub>"}}},{"field":"Current_RMS","FieldUnitSystemID":8,"Settings":{"unit":{"id":8,"factor":0},"TCPanel":{"id":151,"titleTemplate":"I<sub>RMS</sub>@{{ label }}"},"title":"Irms @","supertitle":"Electrical Properties","class":"align-right calculated","width":"140px","listed":false, "hidden":true,"headerAttributes":{"title":"<sub>RMS</sub>"}}},{"field":"Resistance_Iso","FieldUnitSystemID":10,"Settings":{"unit":{"id":10,"factor":0}, "width":"70px", "filter":{"defaultBase": 1000000000,"units": "1000000000"}, "title":"R<sub>iso</sub>", "format":"> {0}", "supertitle":"Electrical Properties", "class":"align-right", "headerAttributes":{"title":"Isolation Resistance"} }},{"field":"dVdt","FieldUnitSystemID":32,"Settings":{"unit":{"id":32,"factor":1}, "width":"80px", "title":"dV/dt", "supertitle":"Electrical Properties", "class":"align-right", "headerAttributes":{"title":"dV/dt"} }},{"field":"Pitch","FieldUnitSystemID":3,"Settings":{"unit":{"id":3,"factor":0.001}, "width":"90px", "title":"Pitch","supertitle":"Dimensions", "filter":{"defaultBase": 0.001,"units": "0.001"}, "precision": 3,"class":"align-right", "headerAttributes":{"title":"Pitch"} }},{"field":"Size_Length","FieldUnitSystemID":3,"Settings":{"unit":{"id":3,"factor":0.001}, "title":"Length","supertitle":"Dimensions", "filter":{"defaultBase": 0.001,"units": "0.001"},"precision": 3, "width": "75px", "class":"align-right", "headerAttributes":{"title":"Length"} }},{"field":"Size_Width","FieldUnitSystemID":3,"Settings":{"unit":{"id":3,"factor":0.001}, "title":"Width","supertitle":"Dimensions", "filter":{"defaultBase": 0.001,"units": "0.001"},"precision": 3, "width": "75px", "class":"align-right", "headerAttributes":{"title":"Width"} }},{"field":"Size_Height","FieldUnitSystemID":3,"Settings":{"unit":{"id":3,"factor":0.001}, "title":"Height","supertitle":"Dimensions", "filter":{"defaultBase": 0.001,"units": "0.001"},"precision": 3, "width": "75px", "class":"align-right", "headerAttributes":{"title":"Height"} }},{"field":"Temperature_MIN","FieldUnitSystemID":4,"Settings":{"unit":{"id":4,"factor":1}, "width":"65px", "title":"T<sub>min</sub>", "supertitle":"Temperature", "class":"align-right", "headerAttributes":{"title":"Minimum Operating Temperature"},  "filter":{"template":"multiselect", "source":true} }},{"field":"Temperature_OPT","FieldUnitSystemID":4,"Settings":{"unit":{"id":4,"factor":1}, "width":"65px", "title":"T<sub>Op</sub>", "supertitle":"Construction", "class":"align-right", "headerAttributes":{"title":"Maximum Operating Temperature"},  "filter":{"template":"multiselect", "source":true} }},{"field":"Assembling_Technology","FieldUnitSystemID":2,"Settings":{"title":"Assembling", "supertitle":"Construction", "filter":{"source": true}, "class":"align-left", "width": 11, "headerAttributes":{"title":"Assembling"} }},{"field":"Frequency_kHz","FieldUnitSystemID":5,"FieldUnitBase":1000.0,"Settings":{"title": "Dummy for property tracking", "filterable": false, "listed":false, "hidden": "true"}},{"field":"Temperature","FieldUnitSystemID":4,"Settings":{"title": "Dummy for property tracking", "filterable": false, "listed":false, "hidden": "true"}},{"field":"Frequency_Mhz","FieldUnitSystemID":5,"FieldUnitBase":1000000.0,"Settings":{"title": "Dummy for property tracking", "filterable": false, "listed":false, "hidden": "true"}},{"field":"VDE","FieldUnitSystemID":35,"Settings":{"title": "Certificates", "supertitle": "General", "filterable": false, "sortable": false, "format":"# if(VDE){ #<a href=\"/redexpert/catalog/application/Caps_Safety/Certificates/#= VDE #.pdf\" target=\"_blank\"><div class=\"grid-column-img certificate #if(VDE==\"WCAP-FTXx_VDE\"){# ENEC #}else{# TUV #}#\" title=\" #if(VDE==\"WCAP-FTXx_VDE\"){# ENEC #}else{# T&Uuml;V #}#\"/></a># } if(ULUS){ #<a href=\"#= ULUS #.pdf\" target=\"_blank\"><div class=\"grid-column-img certificate ULUS\" title=\"UR-US-E345659\"/></a># } if(ULUSTNV){ #<a href=\"#= ULUSTNV #.pdf\" target=\"_blank\"><div class=\"grid-column-img certificate ULUS\" title=\"UR-US-E331896\"/></a># } if(ULCAD){ #<a href=\"#= ULCAD #.pdf\" target=\"_blank\"><div class=\"grid-column-img certificate ULCAD\" title=\"UR-CAD-E345659\"/></a># } if(ULCADTNV){ #<a href=\"#= ULCADTNV #.pdf\" target=\"_blank\"><div class=\"grid-column-img certificate ULCAD\" title=\"UR-CAD-E331896\"/></a># } if(CQC){ #<a href=\"/redexpert/catalog/application/Caps_Safety/Certificates/#= CQC #.pdf\" target=\"_blank\"><div class=\"grid-column-img certificate CQC\" title=\"CQC\"/></a># }#","class":"align-center", "width": "270px", "headerAttributes":{"title":"Certificates"} }},{"field":"EmptyProperty","FieldUnitSystemID":1,"Settings":{"title":"blank-space", "filterable":false, "sortable": false}}],"Panels":[{"PanelID":16,"Title":"Impedance / Frequency","PanelType":"Chart","Position":0,"Settings":{"name": "FZ", "shortTitle":"Z vs. F", "bar": true, "TCID":11, "TCProperty":{"x":"Frequency_Mhz","y":"Impedance_TC"},"xAxis":{"title":{"text":"Frequency (MHz)"},"type":"log", "min": 0.001, "max": 1000,  "axisCrossingValue": 0.001},"yAxis":{"title":{"text":"Impedance (Ω)"},"type":"log", "max": 1000, "axisCrossingValue": 0.01}}},{"PanelID":17,"Title":"Dissipation Factor / Frequency","PanelType":"Chart","Position":2,"Settings":{"name": "FDF", "shortTitle":"DF vs. F", "bar": true, "visible":false, "TCID":12, "TCProperty":{"x":"Frequency_kHz","y":"DF_Frequency_TC"},"xAxis":{"title":{"text":"Frequency (kHz)"},"type":"log", "min": 1, "max": 100},"yAxis":{"title":{"text":"Dissipation Factor (%)"},"type":"log", "min": 0.001, "max":1, "axisCrossingValue": 0.001}}},{"PanelID":18,"Title":"Capacitance / Temperature","PanelType":"Chart","Position":3,"Settings":{"name": "TC", "shortTitle":"C vs. T", "bar": true, "TCID":13, "TCProperty":{"x":"Temperature","y":"Capacitance_nFTC"},"xAxis":{"title":{"text":"Temperature (ºC)"}, "axisCrossingValue": -40, "min": -40, "max": 110, "standard": 20},"yAxis":{"title":{"text":"Capacitance (nF)"},"type":"numeric"}}},{"PanelID":58,"Title":"Capacitance Change / Frequency","PanelType":"Chart","Position":1,"Settings":{"name": "FdC", "shortTitle":"ΔC vs. F", "bar": true, "TCID":44, "TCProperty":{"x":"Frequency_kHz","y":"Capacitance_Change_TC"}, "xAxis":{"title":{"text":"Frequency"},"type":"log", "min": 1, "max": 1000},"yAxis":{"title":{"text":"Capacitance Change"},"axisCrossingValue": -5,"min": -5, "max": 1}}},{"PanelID":59,"Title":"Dissipation Factor / Temperature","PanelType":"Chart","Position":4,"Settings":{"name": "TDF", "shortTitle":"DF vs. T", "bar": true, "visible":false,  "TCID":45, "TCProperty":{"x":"Temperature","y":"DF_Temperature_TC"},"xAxis":{"title":{"text":"Temperature"}, "axisCrossingValue": -40, "min": -40, "max": 110, "standard": 20},"yAxis":{"title":{"text":"Disipation Factor"},"type":"numeric"}}},{"PanelID":150,"Title":"Vrms / Frequency","PanelType":"Chart","Position":5,"Settings":{"name":"VRF","shortTitle":"V<sub>RMS</sub> vs F","bar":true,"visible":true,"TCID":99,"TCProperty":{"x":"Frequency_kHz","y":"Voltage_RMS"},"xAxis":{"title":{"text":"Frequency"},"type":"log", "axisCrossingValue": 0.001},"yAxis":{"title":{"text":"Vrms"},"type":"log", "axisCrossingValue": 0.001}}},{"PanelID":151,"Title":"Irms / Frequency","PanelType":"Chart","Position":6,"Settings":{"name":"IRF","shortTitle":"I<sub>RMS</sub> vs F","bar":true,"visible":false, "TCID":100,"TCProperty":{"x":"Frequency_kHz","y":"Current_RMS"},"xAxis":{"title":{"text":"Frequency"},"type":"log", "axisCrossingValue": 0.001},"yAxis":{"title":{"text":" Irms"},"type":"log", "axisCrossingValue": 0.001}}}],"IconsCSS":"module11-3.3-1.css","UserPreferences":[]}