{"Data": [{"ID": 440272,"Series": "WE-CMBH","Size": "L","Order_Code": "744834101","Is_Internal": false,"Rated_Voltage": 250,"Inductance": 0.001,"Rated_Current": 10,"Resistance_DC": 0.0125,"Size_Length": 0.0325,"Size_Width": 0.028,"Size_Height": 0.0215,"Lines": "2","Temperature_AMB": 70,"Temperature_MAX": 125,"Voltage_Insulation": 1500,"Assembling_Technology": "THT","VDE": "VDE_WE-CMB-CMBH-CMBHC-CMBNiZn"},{"ID": 440273,"Series": "WE-CMBH","Size": "L","Order_Code": "744834622","Is_Internal": false,"Rated_Voltage": 250,"Inductance": 0.0022,"Rated_Current": 6,"Resistance_DC": 0.022,"Size_Length": 0.0325,"Size_Width": 0.028,"Size_Height": 0.0215,"Lines": "2","Temperature_AMB": 70,"Temperature_MAX": 125,"Voltage_Insulation": 1500,"Assembling_Technology": "THT","VDE": "VDE_WE-CMB-CMBH-CMBHC-CMBNiZn"},{"ID": 440274,"Series": "WE-CMBH","Size": "L","Order_Code": "744834433","Is_Internal": false,"Rated_Voltage": 250,"Inductance": 0.0033,"Rated_Current": 5,"Resistance_DC": 0.037,"Size_Length": 0.0325,"Size_Width": 0.028,"Size_Height": 0.0215,"Lines": "2","Temperature_AMB": 70,"Temperature_MAX": 125,"Voltage_Insulation": 1500,"Assembling_Technology": "THT","VDE": "VDE_WE-CMB-CMBH-CMBHC-CMBNiZn"},{"ID": 440275,"Series": "WE-CMBH","Size": "L","Order_Code": "744834405","Is_Internal": false,"Rated_Voltage": 250,"Inductance": 0.005,"Rated_Current": 4,"Resistance_DC": 0.05,"Size_Length": 0.0325,"Size_Width": 0.028,"Size_Height": 0.0215,"Lines": "2","Temperature_AMB": 70,"Temperature_MAX": 125,"Voltage_Insulation": 1500,"Assembling_Technology": "THT","VDE": "VDE_WE-CMB-CMBH-CMBHC-CMBNiZn"},{"ID": 440276,"Series": "WE-CMBH","Size": "L","Order_Code": "744834407","Is_Internal": false,"Rated_Voltage": 250,"Inductance": 0.007,"Rated_Current": 3.5,"Resistance_DC": 0.08,"Size_Length": 0.0325,"Size_Width": 0.028,"Size_Height": 0.0215,"Lines": "2","Temperature_AMB": 70,"Temperature_MAX": 125,"Voltage_Insulation": 1500,"Assembling_Technology": "THT","VDE": "VDE_WE-CMB-CMBH-CMBHC-CMBNiZn"},{"ID": 440277,"Series": "WE-CMBNC","Size": "XS","Order_Code": "7448010911","Is_Internal": false,"Rated_Voltage": 250,"Inductance": 0.011,"Rated_Current": 0.9,"Resistance_DC": 0.48,"Size_Length": 0.014,"Size_Width": 0.0075,"Size_Height": 0.016,"Lines": "2","Temperature_AMB": 70,"Temperature_MAX": 125,"Voltage_Insulation": 1500,"Assembling_Technology": "THT","VDE": "VDE_WE-CMB-CMBH-CMBHC-CMBNiZn"},{"ID": 440278,"Series": "WE-CMBNC","Size": "XS","Order_Code": "7448011008","Is_Internal": false,"Rated_Voltage": 250,"Inductance": 0.008,"Rated_Current": 1,"Resistance_DC": 0.33,"Size_Length": 0.014,"Size_Width": 0.0075,"Size_Height": 0.016,"Lines": "2","Temperature_AMB": 70,"Temperature_MAX": 125,"Voltage_Insulation": 1500,"Assembling_Technology": "THT","VDE": "VDE_WE-CMB-CMBH-CMBHC-CMBNiZn"},{"ID": 440279,"Series": "WE-CMBNC","Size": "XS","Order_Code": "7448011305","Is_Internal": false,"Rated_Voltage": 250,"Inductance": 0.005,"Rated_Current": 1.3,"Resistance_DC": 0.2,"Size_Length": 0.014,"Size_Width": 0.0075,"Size_Height": 0.016,"Lines": "2","Temperature_AMB": 70,"Temperature_MAX": 125,"Voltage_Insulation": 1500,"Assembling_Technology": "THT","VDE": "VDE_WE-CMB-CMBH-CMBHC-CMBNiZn"},{"ID": 440280,"Series": "WE-CMBNC","Size": "XS","Order_Code": "7448012002","Is_Internal": false,"Rated_Voltage": 250,"Inductance": 0.0016,"Rated_Current": 2,"Resistance_DC": 0.09,"Size_Length": 0.014,"Size_Width": 0.0075,"Size_Height": 0.016,"Lines": "2","Temperature_AMB": 70,"Temperature_MAX": 125,"Voltage_Insulation": 1500,"Assembling_Technology": "THT","VDE": "VDE_WE-CMB-CMBH-CMBHC-CMBNiZn"},{"ID": 440281,"Series": "WE-CMBNC","Size": "XS","Order_Code": "7448012501","Is_Internal": false,"Rated_Voltage": 250,"Inductance": 0.001,"Rated_Current": 2.5,"Resistance_DC": 0.05,"Size_Length": 0.014,"Size_Width": 0.0075,"Size_Height": 0.016,"Lines": "2","Temperature_AMB": 70,"Temperature_MAX": 125,"Voltage_Insulation": 1500,"Assembling_Technology": "THT","VDE": "VDE_WE-CMB-CMBH-CMBHC-CMBNiZn"},{"ID": 440282,"Series": "WE-CMBNC","Size": "XS","Order_Code": "7448013501","Is_Internal": false,"Rated_Voltage": 250,"Inductance": 0.0005,"Rated_Current": 3.5,"Resistance_DC": 0.03,"Size_Length": 0.015,"Size_Width": 0.0075,"Size_Height": 0.016,"Lines": "2","Temperature_AMB": 70,"Temperature_MAX": 125,"Voltage_Insulation": 1500,"Assembling_Technology": "THT","VDE": "VDE_WE-CMB-CMBH-CMBHC-CMBNiZn"},{"ID": 440283,"Series": "WE-CMBNC","Size": "XS","Order_Code": "7448014501","Is_Internal": false,"Rated_Voltage": 250,"Inductance": 0.0004,"Rated_Current": 4.5,"Resistance_DC": 0.02,"Size_Length": 0.015,"Size_Width": 0.0075,"Size_Height": 0.016,"Lines": "2","Temperature_AMB": 70,"Temperature_MAX": 125,"Voltage_Insulation": 1500,"Assembling_Technology": "THT","VDE": "VDE_WE-CMB-CMBH-CMBHC-CMBNiZn"},{"ID": 440292,"Series": "WE-CMBNC","Size": "M","Order_Code": "7448030333","Is_Internal": false,"Rated_Voltage": 250,"Inductance": 0.033,"Resistance_DC": 0.09,"Size_Length": 0.022,"Size_Width": 0.0135,"Size_Height": 0.025,"Lines": "2","Temperature_AMB": 70,"Temperature_MAX": 125,"Voltage_Insulation": 1500,"Assembling_Technology": "THT","VDE": "VDE_WE-CMB-CMBH-CMBHC-CMBNiZn"},{"ID": 440293,"Series": "WE-CMBNC","Size": "M","Order_Code": "7448030417","Is_Internal": false,"Rated_Voltage": 250,"Inductance": 0.017,"Rated_Current": 4,"Resistance_DC": 0.05,"Size_Length": 0.022,"Size_Width": 0.0135,"Size_Height": 0.025,"Lines": "2","Temperature_AMB": 70,"Temperature_MAX": 125,"Voltage_Insulation": 1500,"Assembling_Technology": "THT","VDE": "VDE_WE-CMB-CMBH-CMBHC-CMBNiZn"},{"ID": 440294,"Series": "WE-CMBNC","Size": "M","Order_Code": "7448030509","Is_Internal": false,"Rated_Voltage": 250,"Inductance": 0.009,"Rated_Current": 5,"Resistance_DC": 0.028,"Size_Length": 0.022,"Size_Width": 0.0135,"Size_Height": 0.025,"Lines": "2","Temperature_AMB": 70,"Temperature_MAX": 125,"Voltage_Insulation": 1500,"Assembling_Technology": "THT","VDE": "VDE_WE-CMB-CMBH-CMBHC-CMBNiZn"},{"ID": 440295,"Series": "WE-CMBNC","Size": "M","Order_Code": "7448031002","Is_Internal": false,"Rated_Voltage": 250,"Inductance": 0.002,"Rated_Current": 10,"Resistance_DC": 0.006,"Size_Length": 0.023,"Size_Width": 0.017,"Size_Height": 0.025,"Lines": "2","Temperature_AMB": 70,"Temperature_MAX": 125,"Voltage_Insulation": 1500,"Assembling_Technology": "THT","VDE": "VDE_WE-CMB-CMBH-CMBHC-CMBNiZn"},{"ID": 440296,"Series": "WE-CMBNC","Size": "M","Order_Code": "7448031501","Is_Internal": false,"Rated_Voltage": 250,"Inductance": 0.001,"Rated_Current": 15,"Resistance_DC": 0.003,"Size_Length": 0.023,"Size_Width": 0.017,"Size_Height": 0.025,"Lines": "2","Temperature_AMB": 70,"Temperature_MAX": 125,"Voltage_Insulation": 1500,"Assembling_Technology": "THT","VDE": "VDE_WE-CMB-CMBH-CMBHC-CMBNiZn"},{"ID": 440297,"Series": "WE-CMBNC","Size": "L","Order_Code": "7448040382","Is_Internal": false,"Rated_Voltage": 250,"Inductance": 0.082,"Rated_Current": 2.5,"Resistance_DC": 0.17,"Size_Length": 0.0275,"Size_Width": 0.018,"Size_Height": 0.032,"Lines": "2","Temperature_AMB": 70,"Temperature_MAX": 125,"Voltage_Insulation": 1500,"Assembling_Technology": "THT","VDE": "VDE_WE-CMB-CMBH-CMBHC-CMBNiZn"},{"ID": 440298,"Series": "WE-CMBNC","Size": "L","Order_Code": "7448040435","Is_Internal": false,"Rated_Voltage": 250,"Inductance": 0.035,"Rated_Current": 3.5,"Resistance_DC": 0.08,"Size_Length": 0.0275,"Size_Width": 0.018,"Size_Height": 0.032,"Lines": "2","Temperature_AMB": 70,"Temperature_MAX": 125,"Voltage_Insulation": 1500,"Assembling_Technology": "THT","VDE": "VDE_WE-CMB-CMBH-CMBHC-CMBNiZn"},{"ID": 440299,"Series": "WE-CMBNC","Size": "L","Order_Code": "7448040515","Is_Internal": false,"Rated_Voltage": 250,"Inductance": 0.015,"Rated_Current": 5,"Resistance_DC": 0.038,"Size_Length": 0.0275,"Size_Width": 0.018,"Size_Height": 0.032,"Lines": "2","Temperature_AMB": 70,"Temperature_MAX": 125,"Voltage_Insulation": 1500,"Assembling_Technology": "THT","VDE": "VDE_WE-CMB-CMBH-CMBHC-CMBNiZn"},{"ID": 440300,"Series": "WE-CMBNC","Size": "L","Order_Code": "7448040707","Is_Internal": false,"Rated_Voltage": 250,"Inductance": 0.007,"Rated_Current": 7,"Resistance_DC": 0.02,"Size_Length": 0.0275,"Size_Width": 0.019,"Size_Height": 0.032,"Lines": "2","Temperature_AMB": 70,"Temperature_MAX": 125,"Voltage_Insulation": 1500,"Assembling_Technology": "THT","VDE": "VDE_WE-CMB-CMBH-CMBHC-CMBNiZn"},{"ID": 440301,"Series": "WE-CMBNC","Size": "L","Order_Code": "7448041104","Is_Internal": false,"Rated_Voltage": 250,"Inductance": 0.004,"Rated_Current": 11,"Resistance_DC": 0.0085,"Size_Length": 0.0275,"Size_Width": 0.019,"Size_Height": 0.032,"Lines": "2","Temperature_AMB": 70,"Temperature_MAX": 125,"Voltage_Insulation": 1500,"Assembling_Technology": "THT","VDE": "VDE_WE-CMB-CMBH-CMBHC-CMBNiZn"},{"ID": 440302,"Series": "WE-CMBNC","Size": "L","Order_Code": "7448041502","Is_Internal": false,"Rated_Voltage": 250,"Inductance": 0.002,"Rated_Current": 15,"Resistance_DC": 0.005,"Size_Length": 0.03,"Size_Width": 0.019,"Size_Height": 0.032,"Lines": "2","Temperature_AMB": 70,"Temperature_MAX": 125,"Voltage_Insulation": 1500,"Assembling_Technology": "THT","VDE": "VDE_WE-CMB-CMBH-CMBHC-CMBNiZn"},{"ID": 440303,"Series": "WE-CMBNC","Size": "L","Order_Code": "7448041801","Is_Internal": false,"Rated_Voltage": 250,"Inductance": 0.0015,"Rated_Current": 18,"Resistance_DC": 0.0032,"Size_Length": 0.03,"Size_Width": 0.019,"Size_Height": 0.032,"Lines": "2","Temperature_AMB": 70,"Temperature_MAX": 125,"Voltage_Insulation": 1500,"Assembling_Technology": "THT","VDE": "VDE_WE-CMB-CMBH-CMBHC-CMBNiZn"},{"ID": 440304,"Series": "WE-CMBNC","Size": "L","Order_Code": "7448042001","Is_Internal": false,"Rated_Voltage": 250,"Inductance": 0.001,"Rated_Current": 20,"Resistance_DC": 0.0024,"Size_Length": 0.03,"Size_Width": 0.019,"Size_Height": 0.032,"Lines": "2","Temperature_AMB": 70,"Temperature_MAX": 125,"Voltage_Insulation": 1500,"Assembling_Technology": "THT","VDE": "VDE_WE-CMB-CMBH-CMBHC-CMBNiZn"},{"ID": 440305,"Series": "WE-CMBNC","Size": "XL","Order_Code": "7448050219","Is_Internal": false,"Rated_Voltage": 250,"Inductance": 0.19,"Rated_Current": 2,"Resistance_DC": 0.31,"Size_Length": 0.033,"Size_Width": 0.019,"Size_Height": 0.039,"Lines": "2","Temperature_AMB": 70,"Temperature_MAX": 125,"Voltage_Insulation": 1500,"Assembling_Technology": "THT","VDE": "VDE_WE-CMB-CMBH-CMBHC-CMBNiZn"},{"ID": 440306,"Series": "WE-CMBNC","Size": "XL","Order_Code": "7448050490","Is_Internal": false,"Rated_Voltage": 250,"Inductance": 0.09,"Rated_Current": 3.5,"Resistance_DC": 0.11,"Size_Length": 0.033,"Size_Width": 0.019,"Size_Height": 0.039,"Lines": "2","Temperature_AMB": 70,"Temperature_MAX": 125,"Voltage_Insulation": 1500,"Assembling_Technology": "THT","VDE": "VDE_WE-CMB-CMBH-CMBHC-CMBNiZn"},{"ID": 440307,"Series": "WE-CMBNC","Size": "XL","Order_Code": "7448050530","Is_Internal": false,"Rated_Voltage": 250,"Inductance": 0.03,"Rated_Current": 5,"Resistance_DC": 0.046,"Size_Length": 0.033,"Size_Width": 0.023,"Size_Height": 0.036,"Lines": "2","Temperature_AMB": 70,"Temperature_MAX": 125,"Voltage_Insulation": 1500,"Assembling_Technology": "THT","VDE": "VDE_WE-CMB-CMBH-CMBHC-CMBNiZn"},{"ID": 440308,"Series": "WE-CMBNC","Size": "XL","Order_Code": "7448051012","Is_Internal": false,"Rated_Voltage": 250,"Inductance": 0.012,"Rated_Current": 10,"Resistance_DC": 0.015,"Size_Length": 0.034,"Size_Width": 0.023,"Size_Height": 0.036,"Lines": "2","Temperature_AMB": 70,"Temperature_MAX": 125,"Voltage_Insulation": 1500,"Assembling_Technology": "THT","VDE": "VDE_WE-CMB-CMBH-CMBHC-CMBNiZn"},{"ID": 440309,"Series": "WE-CMBNC","Size": "XL","Order_Code": "7448051804","Is_Internal": false,"Rated_Voltage": 250,"Inductance": 0.0045,"Rated_Current": 18,"Resistance_DC": 0.0042,"Size_Length": 0.036,"Size_Width": 0.023,"Size_Height": 0.036,"Lines": "2","Temperature_AMB": 70,"Temperature_MAX": 125,"Voltage_Insulation": 1500,"Assembling_Technology": "THT","VDE": "VDE_WE-CMB-CMBH-CMBHC-CMBNiZn"},{"ID": 440310,"Series": "WE-CMBNC","Size": "XL","Order_Code": "7448052303","Is_Internal": false,"Rated_Voltage": 250,"Inductance": 0.003,"Rated_Current": 23,"Resistance_DC": 0.003,"Size_Length": 0.036,"Size_Width": 0.023,"Size_Height": 0.036,"Lines": "2","Temperature_AMB": 70,"Temperature_MAX": 125,"Voltage_Insulation": 1500,"Assembling_Technology": "THT","VDE": "VDE_WE-CMB-CMBH-CMBHC-CMBNiZn"},{"ID": 440311,"Series": "WE-CMBNC","Size": "XL","Order_Code": "7448052502","Is_Internal": false,"Rated_Voltage": 250,"Inductance": 0.0025,"Rated_Current": 25,"Resistance_DC": 0.0022,"Size_Length": 0.036,"Size_Width": 0.023,"Size_Height": 0.036,"Lines": "2","Temperature_AMB": 70,"Temperature_MAX": 125,"Voltage_Insulation": 1500,"Assembling_Technology": "THT","VDE": "VDE_WE-CMB-CMBH-CMBHC-CMBNiZn"},{"ID": 440312,"Series": "WE-CMBNC","Size": "XL","Order_Code": "7448053201","Is_Internal": false,"Rated_Voltage": 250,"Inductance": 0.0009,"Rated_Current": 32,"Resistance_DC": 0.0011,"Size_Length": 0.037,"Size_Width": 0.023,"Size_Height": 0.036,"Lines": "2","Temperature_AMB": 70,"Temperature_MAX": 125,"Voltage_Insulation": 1500,"Assembling_Technology": "THT","VDE": "VDE_WE-CMB-CMBH-CMBHC-CMBNiZn"},{"ID": 440313,"Series": "WE-CMBNC","Size": "XXL","Order_Code": "7448060535","Is_Internal": false,"Rated_Voltage": 250,"Inductance": 0.035,"Rated_Current": 5,"Resistance_DC": 0.09,"Size_Length": 0.042,"Size_Width": 0.027,"Size_Height": 0.046,"Lines": "2","Temperature_AMB": 70,"Temperature_MAX": 125,"Voltage_Insulation": 1500,"Assembling_Technology": "THT","VDE": "VDE_WE-CMB-CMBH-CMBHC-CMBNiZn"},{"ID": 440314,"Series": "WE-CMBNC","Size": "XXL","Order_Code": "7448060620","Is_Internal": false,"Rated_Voltage": 250,"Inductance": 0.02,"Rated_Current": 6,"Resistance_DC": 0.045,"Size_Length": 0.042,"Size_Width": 0.027,"Size_Height": 0.046,"Lines": "2","Temperature_AMB": 70,"Temperature_MAX": 125,"Voltage_Insulation": 1500,"Assembling_Technology": "THT","VDE": "VDE_WE-CMB-CMBH-CMBHC-CMBNiZn"},{"ID": 440315,"Series": "WE-CMBNC","Size": "XXL","Order_Code": "7448060814","Is_Internal": false,"Rated_Voltage": 250,"Inductance": 0.014,"Rated_Current": 8,"Resistance_DC": 0.027,"Size_Length": 0.043,"Size_Width": 0.027,"Size_Height": 0.046,"Lines": "2","Temperature_AMB": 70,"Temperature_MAX": 125,"Voltage_Insulation": 1500,"Assembling_Technology": "THT","VDE": "VDE_WE-CMB-CMBH-CMBHC-CMBNiZn"},{"ID": 440316,"Series": "WE-CMBNC","Size": "XXL","Order_Code": "7448061309","Is_Internal": false,"Rated_Voltage": 250,"Inductance": 0.009,"Rated_Current": 13,"Resistance_DC": 0.015,"Size_Length": 0.044,"Size_Width": 0.027,"Size_Height": 0.046,"Lines": "2","Temperature_AMB": 70,"Temperature_MAX": 125,"Voltage_Insulation": 1500,"Assembling_Technology": "THT","VDE": "VDE_WE-CMB-CMBH-CMBHC-CMBNiZn"},{"ID": 440317,"Series": "WE-CMBNC","Size": "XXL","Order_Code": "7448061507","Is_Internal": false,"Rated_Voltage": 250,"Inductance": 0.007,"Rated_Current": 15,"Resistance_DC": 0.0095,"Size_Length": 0.046,"Size_Width": 0.027,"Size_Height": 0.046,"Lines": "2","Temperature_AMB": 70,"Temperature_MAX": 125,"Voltage_Insulation": 1500,"Assembling_Technology": "THT","VDE": "VDE_WE-CMB-CMBH-CMBHC-CMBNiZn"},{"ID": 440318,"Series": "WE-CMBNC","Size": "XXL","Order_Code": "7448062105","Is_Internal": false,"Rated_Voltage": 250,"Inductance": 0.005,"Rated_Current": 21,"Resistance_DC": 0.0065,"Size_Length": 0.046,"Size_Width": 0.027,"Size_Height": 0.046,"Lines": "2","Temperature_AMB": 70,"Temperature_MAX": 125,"Voltage_Insulation": 1500,"Assembling_Technology": "THT","VDE": "VDE_WE-CMB-CMBH-CMBHC-CMBNiZn"},{"ID": 440319,"Series": "WE-CMBNC","Size": "XXL","Order_Code": "7448062603","Is_Internal": false,"Rated_Voltage": 250,"Inductance": 0.003,"Rated_Current": 26,"Resistance_DC": 0.0045,"Size_Length": 0.047,"Size_Width": 0.027,"Size_Height": 0.046,"Lines": "2","Temperature_AMB": 70,"Temperature_MAX": 125,"Voltage_Insulation": 1500,"Assembling_Technology": "THT","VDE": "VDE_WE-CMB-CMBH-CMBHC-CMBNiZn"},{"ID": 440320,"Series": "WE-CMBNC","Size": "XXL","Order_Code": "7448063801","Is_Internal": false,"Rated_Voltage": 250,"Inductance": 0.0015,"Rated_Current": 38,"Resistance_DC": 0.0023,"Size_Length": 0.048,"Size_Width": 0.027,"Size_Height": 0.046,"Lines": "2","Temperature_AMB": 70,"Temperature_MAX": 125,"Voltage_Insulation": 1500,"Assembling_Technology": "THT","VDE": "VDE_WE-CMB-CMBH-CMBHC-CMBNiZn"},{"ID": 440321,"Series": "WE-CMB","Size": "XS","Order_Code": "744821039","Is_Internal": false,"Rated_Voltage": 250,"Inductance": 0.039,"Rated_Current": 0.3,"Resistance_DC": 3,"Size_Length": 0.0145,"Size_Width": 0.007,"Size_Height": 0.0165,"Lines": "2","Temperature_AMB": 70,"Temperature_MAX": 125,"Voltage_Insulation": 1500,"Assembling_Technology": "THT","VDE": "VDE_WE-CMB-CMBH-CMBHC-CMBNiZn"},{"ID": 440322,"Series": "WE-CMB","Size": "XS","Order_Code": "744821110","Is_Internal": false,"Rated_Voltage": 250,"Inductance": 0.01,"Rated_Current": 0.7,"Resistance_DC": 0.35,"Size_Length": 0.0145,"Size_Width": 0.007,"Size_Height": 0.0165,"Lines": "2","Temperature_AMB": 70,"Temperature_MAX": 125,"Voltage_Insulation": 1500,"Assembling_Technology": "THT","VDE": "VDE_WE-CMB-CMBH-CMBHC-CMBNiZn"},{"ID": 440323,"Series": "WE-CMB","Size": "XS","Order_Code": "744821120","Is_Internal": false,"Rated_Voltage": 250,"Inductance": 0.02,"Rated_Current": 0.5,"Resistance_DC": 1,"Size_Length": 0.0145,"Size_Width": 0.007,"Size_Height": 0.0165,"Lines": "2","Temperature_AMB": 70,"Temperature_MAX": 125,"Voltage_Insulation": 1500,"Assembling_Technology": "THT","VDE": "VDE_WE-CMB-CMBH-CMBHC-CMBNiZn"},{"ID": 440324,"Series": "WE-CMB","Size": "XS","Order_Code": "744821150","Is_Internal": false,"Rated_Voltage": 250,"Inductance": 0.005,"Rated_Current": 1,"Resistance_DC": 0.2,"Size_Length": 0.0145,"Size_Width": 0.007,"Size_Height": 0.0165,"Lines": "2","Temperature_AMB": 70,"Temperature_MAX": 125,"Voltage_Insulation": 1500,"Assembling_Technology": "THT","VDE": "VDE_WE-CMB-CMBH-CMBHC-CMBNiZn"},{"ID": 440325,"Series": "WE-CMB","Size": "XS","Order_Code": "744821201","Is_Internal": false,"Rated_Voltage": 250,"Inductance": 0.001,"Rated_Current": 2,"Resistance_DC": 0.0445,"Size_Length": 0.0145,"Size_Width": 0.007,"Size_Height": 0.0165,"Lines": "2","Temperature_AMB": 70,"Temperature_MAX": 125,"Voltage_Insulation": 1500,"Assembling_Technology": "THT","VDE": "VDE_WE-CMB-CMBH-CMBHC-CMBNiZn"},{"ID": 440326,"Series": "WE-CMB","Size": "XS","Order_Code": "744821240","Is_Internal": false,"Rated_Voltage": 250,"Inductance": 0.004,"Rated_Current": 1.5,"Resistance_DC": 0.14,"Size_Length": 0.0145,"Size_Width": 0.007,"Size_Height": 0.0165,"Lines": "2","Temperature_AMB": 70,"Temperature_MAX": 125,"Voltage_Insulation": 1500,"Assembling_Technology": "THT","VDE": "VDE_WE-CMB-CMBH-CMBHC-CMBNiZn"},{"ID": 440327,"Series": "WE-CMB","Size": "S","Order_Code": "744822110","Is_Internal": false,"Rated_Voltage": 250,"Inductance": 0.01,"Rated_Current": 1,"Resistance_DC": 0.36,"Size_Length": 0.017,"Size_Width": 0.012,"Size_Height": 0.0205,"Lines": "2","Temperature_AMB": 70,"Temperature_MAX": 125,"Voltage_Insulation": 1500,"Assembling_Technology": "THT","VDE": "VDE_WE-CMB-CMBH-CMBHC-CMBNiZn"},{"ID": 440328,"Series": "WE-CMB","Size": "S","Order_Code": "744822120","Is_Internal": false,"Rated_Voltage": 250,"Inductance": 0.02,"Rated_Current": 0.5,"Resistance_DC": 0.54,"Size_Length": 0.017,"Size_Width": 0.012,"Size_Height": 0.0205,"Lines": "2","Temperature_AMB": 70,"Temperature_MAX": 125,"Voltage_Insulation": 1500,"Assembling_Technology": "THT","VDE": "VDE_WE-CMB-CMBH-CMBHC-CMBNiZn"},{"ID": 440329,"Series": "WE-CMB","Size": "S","Order_Code": "744822222","Is_Internal": false,"Rated_Voltage": 250,"Inductance": 0.0022,"Rated_Current": 2,"Resistance_DC": 0.07,"Size_Length": 0.017,"Size_Width": 0.012,"Size_Height": 0.0205,"Lines": "2","Temperature_AMB": 70,"Temperature_MAX": 125,"Voltage_Insulation": 1500,"Assembling_Technology": "THT","VDE": "VDE_WE-CMB-CMBH-CMBHC-CMBNiZn"},{"ID": 440331,"Series": "WE-CMB","Size": "S","Order_Code": "744822233","Is_Internal": false,"Rated_Voltage": 250,"Inductance": 0.0033,"Rated_Current": 1.5,"Resistance_DC": 0.12,"Size_Length": 0.017,"Size_Width": 0.012,"Size_Height": 0.0205,"Lines": "2","Temperature_AMB": 70,"Temperature_MAX": 125,"Voltage_Insulation": 1500,"Assembling_Technology": "THT","VDE": "VDE_WE-CMB-CMBH-CMBHC-CMBNiZn"},{"ID": 440332,"Series": "WE-CMB","Size": "S","Order_Code": "744822301","Is_Internal": false,"Rated_Voltage": 250,"Inductance": 0.001,"Rated_Current": 3,"Resistance_DC": 0.035,"Size_Length": 0.017,"Size_Width": 0.012,"Size_Height": 0.0205,"Lines": "2","Temperature_AMB": 70,"Temperature_MAX": 125,"Voltage_Insulation": 1500,"Assembling_Technology": "THT","VDE": "VDE_WE-CMB-CMBH-CMBHC-CMBNiZn"},{"ID": 440333,"Series": "WE-CMB","Size": "M","Order_Code": "744823220","Is_Internal": false,"Rated_Voltage": 250,"Inductance": 0.02,"Rated_Current": 1.5,"Resistance_DC": 0.27,"Size_Length": 0.023,"Size_Width": 0.013,"Size_Height": 0.024,"Lines": "2","Temperature_AMB": 70,"Temperature_MAX": 125,"Voltage_Insulation": 1500,"Assembling_Technology": "THT","VDE": "VDE_WE-CMB-CMBH-CMBHC-CMBNiZn"},{"ID": 440334,"Series": "WE-CMB","Size": "M","Order_Code": "744823210","Is_Internal": false,"Rated_Voltage": 250,"Inductance": 0.01,"Rated_Current": 2,"Resistance_DC": 0.125,"Size_Length": 0.023,"Size_Width": 0.013,"Size_Height": 0.024,"Lines": "2","Temperature_AMB": 70,"Temperature_MAX": 125,"Voltage_Insulation": 1500,"Assembling_Technology": "THT","VDE": "VDE_WE-CMB-CMBH-CMBHC-CMBNiZn"},{"ID": 440335,"Series": "WE-CMB","Size": "M","Order_Code": "744823305","Is_Internal": false,"Rated_Voltage": 250,"Inductance": 0.005,"Rated_Current": 2.5,"Resistance_DC": 0.095,"Size_Length": 0.023,"Size_Width": 0.013,"Size_Height": 0.024,"Lines": "2","Temperature_AMB": 70,"Temperature_MAX": 125,"Voltage_Insulation": 1500,"Assembling_Technology": "THT","VDE": "VDE_WE-CMB-CMBH-CMBHC-CMBNiZn"},{"ID": 440336,"Series": "WE-CMB","Size": "M","Order_Code": "744823333","Is_Internal": false,"Rated_Voltage": 250,"Inductance": 0.0033,"Rated_Current": 2.5,"Resistance_DC": 0.06,"Size_Length": 0.023,"Size_Width": 0.013,"Size_Height": 0.024,"Lines": "2","Temperature_AMB": 70,"Temperature_MAX": 125,"Voltage_Insulation": 1500,"Assembling_Technology": "THT","VDE": "VDE_WE-CMB-CMBH-CMBHC-CMBNiZn"},{"ID": 440337,"Series": "WE-CMB","Size": "M","Order_Code": "744823422","Is_Internal": false,"Rated_Voltage": 250,"Inductance": 0.0022,"Rated_Current": 4,"Resistance_DC": 0.03,"Size_Length": 0.023,"Size_Width": 0.013,"Size_Height": 0.024,"Lines": "2","Temperature_AMB": 70,"Temperature_MAX": 125,"Voltage_Insulation": 1500,"Assembling_Technology": "THT","VDE": "VDE_WE-CMB-CMBH-CMBHC-CMBNiZn"},{"ID": 440338,"Series": "WE-CMB","Size": "M","Order_Code": "744823601","Is_Internal": false,"Rated_Voltage": 250,"Inductance": 0.001,"Rated_Current": 6,"Resistance_DC": 0.013,"Size_Length": 0.023,"Size_Width": 0.013,"Size_Height": 0.024,"Lines": "2","Temperature_AMB": 70,"Temperature_MAX": 125,"Voltage_Insulation": 1500,"Assembling_Technology": "THT","VDE": "VDE_WE-CMB-CMBH-CMBHC-CMBNiZn"},{"ID": 440339,"Series": "WE-CMB","Size": "L","Order_Code": "744824101","Is_Internal": false,"Rated_Voltage": 250,"Inductance": 0.001,"Rated_Current": 10,"Resistance_DC": 0.007,"Size_Length": 0.027,"Size_Width": 0.018,"Size_Height": 0.031,"Lines": "2","Temperature_AMB": 70,"Temperature_MAX": 125,"Voltage_Insulation": 1500,"Assembling_Technology": "THT","VDE": "VDE_WE-CMB-CMBH-CMBHC-CMBNiZn"},{"ID": 440340,"Series": "WE-CMB","Size": "L","Order_Code": "744824220","Is_Internal": false,"Rated_Voltage": 250,"Inductance": 0.02,"Rated_Current": 2,"Resistance_DC": 0.22,"Size_Length": 0.027,"Size_Width": 0.018,"Size_Height": 0.031,"Lines": "2","Temperature_AMB": 70,"Temperature_MAX": 125,"Voltage_Insulation": 1500,"Assembling_Technology": "THT","VDE": "VDE_WE-CMB-CMBH-CMBHC-CMBNiZn"},{"ID": 440341,"Series": "WE-CMB","Size": "L","Order_Code": "744824310","Is_Internal": false,"Rated_Voltage": 250,"Inductance": 0.01,"Rated_Current": 3,"Resistance_DC": 0.105,"Size_Length": 0.027,"Size_Width": 0.018,"Size_Height": 0.031,"Lines": "2","Temperature_AMB": 70,"Temperature_MAX": 125,"Voltage_Insulation": 1500,"Assembling_Technology": "THT","VDE": "VDE_WE-CMB-CMBH-CMBHC-CMBNiZn"},{"ID": 440344,"Series": "WE-CMB","Size": "L","Order_Code": "744824433","Is_Internal": false,"Rated_Voltage": 250,"Inductance": 0.0033,"Rated_Current": 4,"Resistance_DC": 0.035,"Size_Length": 0.027,"Size_Width": 0.018,"Size_Height": 0.031,"Lines": "2","Temperature_AMB": 70,"Temperature_MAX": 125,"Voltage_Insulation": 1500,"Assembling_Technology": "THT","VDE": "VDE_WE-CMB-CMBH-CMBHC-CMBNiZn"},{"ID": 440345,"Series": "WE-CMB","Size": "L","Order_Code": "744824622","Is_Internal": false,"Rated_Voltage": 250,"Inductance": 0.0022,"Rated_Current": 6,"Resistance_DC": 0.02,"Size_Length": 0.027,"Size_Width": 0.018,"Size_Height": 0.031,"Lines": "2","Temperature_AMB": 70,"Temperature_MAX": 125,"Voltage_Insulation": 1500,"Assembling_Technology": "THT","VDE": "VDE_WE-CMB-CMBH-CMBHC-CMBNiZn"},{"ID": 440346,"Series": "WE-CMB","Size": "XL","Order_Code": "7448251201","Is_Internal": false,"Rated_Voltage": 250,"Inductance": 0.001,"Rated_Current": 12,"Resistance_DC": 0.009,"Size_Length": 0.03,"Size_Width": 0.021,"Size_Height": 0.033,"Lines": "2","Temperature_AMB": 70,"Temperature_MAX": 125,"Voltage_Insulation": 1500,"Assembling_Technology": "THT","VDE": "VDE_WE-CMB-CMBH-CMBHC-CMBNiZn"},{"ID": 440347,"Series": "WE-CMB","Size": "XL","Order_Code": "744825320","Is_Internal": false,"Rated_Voltage": 250,"Inductance": 0.02,"Rated_Current": 3,"Resistance_DC": 0.16,"Size_Length": 0.03,"Size_Width": 0.021,"Size_Height": 0.033,"Lines": "2","Temperature_AMB": 70,"Temperature_MAX": 125,"Voltage_Insulation": 1500,"Assembling_Technology": "THT","VDE": "VDE_WE-CMB-CMBH-CMBHC-CMBNiZn"},{"ID": 440349,"Series": "WE-CMB","Size": "XL","Order_Code": "744825433","Is_Internal": false,"Rated_Voltage": 250,"Inductance": 0.033,"Rated_Current": 3,"Resistance_DC": 0.21,"Size_Length": 0.03,"Size_Width": 0.021,"Size_Height": 0.033,"Lines": "2","Temperature_AMB": 70,"Temperature_MAX": 125,"Voltage_Insulation": 1500,"Assembling_Technology": "THT","VDE": "VDE_WE-CMB-CMBH-CMBHC-CMBNiZn"},{"ID": 440350,"Series": "WE-CMB","Size": "XL","Order_Code": "744825510","Is_Internal": false,"Rated_Voltage": 250,"Inductance": 0.01,"Rated_Current": 5,"Resistance_DC": 0.055,"Size_Length": 0.03,"Size_Width": 0.021,"Size_Height": 0.033,"Lines": "2","Temperature_AMB": 70,"Temperature_MAX": 125,"Voltage_Insulation": 1500,"Assembling_Technology": "THT","VDE": "VDE_WE-CMB-CMBH-CMBHC-CMBNiZn"},{"ID": 440351,"Series": "WE-CMB","Size": "XL","Order_Code": "7448256033","Is_Internal": false,"Rated_Voltage": 250,"Inductance": 0.0033,"Rated_Current": 6,"Resistance_DC": 0.025,"Size_Length": 0.03,"Size_Width": 0.021,"Size_Height": 0.033,"Lines": "2","Temperature_AMB": 70,"Temperature_MAX": 125,"Voltage_Insulation": 1500,"Assembling_Technology": "THT","VDE": "VDE_WE-CMB-CMBH-CMBHC-CMBNiZn"},{"ID": 440352,"Series": "WE-CMB","Size": "XL","Order_Code": "744825605","Is_Internal": false,"Rated_Voltage": 250,"Inductance": 0.005,"Rated_Current": 6,"Resistance_DC": 0.045,"Size_Length": 0.03,"Size_Width": 0.021,"Size_Height": 0.033,"Lines": "2","Temperature_AMB": 70,"Temperature_MAX": 125,"Voltage_Insulation": 1500,"Assembling_Technology": "THT","VDE": "VDE_WE-CMB-CMBH-CMBHC-CMBNiZn"},{"ID": 440353,"Series": "WE-CMB","Size": "XL","Order_Code": "7448258022","Is_Internal": false,"Rated_Voltage": 250,"Inductance": 0.0022,"Rated_Current": 8,"Resistance_DC": 0.014,"Size_Length": 0.03,"Size_Width": 0.021,"Size_Height": 0.033,"Lines": "2","Temperature_AMB": 70,"Temperature_MAX": 125,"Voltage_Insulation": 1500,"Assembling_Technology": "THT","VDE": "VDE_WE-CMB-CMBH-CMBHC-CMBNiZn"},{"ID": 440354,"Series": "WE-CMB","Size": "XXL","Order_Code": "7448261418","Is_Internal": false,"Rated_Voltage": 250,"Inductance": 0.0018,"Rated_Current": 14,"Resistance_DC": 0.0079,"Size_Length": 0.042,"Size_Width": 0.0225,"Size_Height": 0.041,"Lines": "2","Temperature_AMB": 70,"Temperature_MAX": 125,"Voltage_Insulation": 1500,"Assembling_Technology": "THT","VDE": "VDE_WE-CMB-CMBH-CMBHC-CMBNiZn"},{"ID": 440355,"Series": "WE-CMB","Size": "XXL","Order_Code": "7448262013","Is_Internal": false,"Rated_Voltage": 250,"Inductance": 0.0013,"Rated_Current": 20,"Resistance_DC": 0.0047,"Size_Length": 0.042,"Size_Width": 0.0225,"Size_Height": 0.041,"Lines": "2","Temperature_AMB": 70,"Temperature_MAX": 125,"Voltage_Insulation": 1500,"Assembling_Technology": "THT","VDE": "VDE_WE-CMB-CMBH-CMBHC-CMBNiZn"},{"ID": 440356,"Series": "WE-CMB","Size": "XXL","Order_Code": "7448262510","Is_Internal": false,"Rated_Voltage": 250,"Inductance": 0.001,"Rated_Current": 25,"Resistance_DC": 0.0036,"Size_Length": 0.042,"Size_Width": 0.0225,"Size_Height": 0.041,"Lines": "2","Temperature_AMB": 70,"Temperature_MAX": 125,"Voltage_Insulation": 1500,"Assembling_Technology": "THT","VDE": "VDE_WE-CMB-CMBH-CMBHC-CMBNiZn"},{"ID": 440357,"Series": "WE-CMB","Size": "XXL","Order_Code": "7448263505","Is_Internal": false,"Rated_Voltage": 250,"Inductance": 0.0005,"Rated_Current": 35,"Resistance_DC": 0.0017,"Size_Length": 0.042,"Size_Width": 0.0225,"Size_Height": 0.041,"Lines": "2","Temperature_AMB": 70,"Temperature_MAX": 125,"Voltage_Insulation": 1500,"Assembling_Technology": "THT","VDE": "VDE_WE-CMB-CMBH-CMBHC-CMBNiZn"},{"ID": 440358,"Series": "WE-CMB HC","Size": "S","Order_Code": "74482210002","Is_Internal": false,"Rated_Voltage": 250,"Inductance": 0.000175,"Rated_Current": 10,"Resistance_DC": 0.004,"Size_Length": 0.018,"Size_Width": 0.014,"Size_Height": 0.021,"Lines": "2","Temperature_AMB": 70,"Temperature_MAX": 125,"Voltage_Insulation": 1500,"Assembling_Technology": "THT","VDE": "VDE_WE-CMB-CMBH-CMBHC-CMBNiZn"},{"ID": 440359,"Series": "WE-CMB HC","Size": "S","Order_Code": "7448229004","Is_Internal": false,"Rated_Voltage": 250,"Inductance": 0.00035,"Rated_Current": 8.5,"Resistance_DC": 0.007,"Size_Length": 0.018,"Size_Width": 0.014,"Size_Height": 0.021,"Lines": "2","Temperature_AMB": 70,"Temperature_MAX": 125,"Voltage_Insulation": 1500,"Assembling_Technology": "THT","VDE": "VDE_WE-CMB-CMBH-CMBHC-CMBNiZn"},{"ID": 440360,"Series": "WE-CMB HC","Size": "S","Order_Code": "7448227005","Is_Internal": false,"Rated_Voltage": 250,"Inductance": 0.00045,"Rated_Current": 6.5,"Resistance_DC": 0.01,"Size_Length": 0.018,"Size_Width": 0.014,"Size_Height": 0.021,"Lines": "2","Temperature_AMB": 70,"Temperature_MAX": 125,"Voltage_Insulation": 1500,"Assembling_Technology": "THT","VDE": "VDE_WE-CMB-CMBH-CMBHC-CMBNiZn"},{"ID": 440361,"Series": "WE-CMB HC","Size": "S","Order_Code": "7448225007","Is_Internal": false,"Rated_Voltage": 250,"Inductance": 0.0007,"Rated_Current": 5,"Resistance_DC": 0.015,"Size_Length": 0.018,"Size_Width": 0.014,"Size_Height": 0.021,"Lines": "2","Temperature_AMB": 70,"Temperature_MAX": 125,"Voltage_Insulation": 1500,"Assembling_Technology": "THT","VDE": "VDE_WE-CMB-CMBH-CMBHC-CMBNiZn"},{"ID": 440362,"Series": "WE-CMB NiZn","Size": "XS","Order_Code": "744841414","Is_Internal": false,"Rated_Voltage": 250,"Inductance": 1.4E-05,"Rated_Current": 4,"Resistance_DC": 0.015,"Size_Length": 0.015,"Size_Width": 0.007,"Size_Height": 0.0165,"Lines": "2","Temperature_AMB": 70,"Temperature_MAX": 125,"Voltage_Insulation": 1500,"Assembling_Technology": "THT","VDE": "VDE_WE-CMB-CMBH-CMBHC-CMBNiZn"},{"ID": 440363,"Series": "WE-CMB NiZn","Size": "XS","Order_Code": "744841330","Is_Internal": false,"Rated_Voltage": 250,"Inductance": 3E-05,"Rated_Current": 3,"Resistance_DC": 0.026,"Size_Length": 0.015,"Size_Width": 0.007,"Size_Height": 0.0165,"Lines": "2","Temperature_AMB": 70,"Temperature_MAX": 125,"Voltage_Insulation": 1500,"Assembling_Technology": "THT","VDE": "VDE_WE-CMB-CMBH-CMBHC-CMBNiZn"},{"ID": 440364,"Series": "WE-CMB NiZn","Size": "XS","Order_Code": "744841247","Is_Internal": false,"Rated_Voltage": 250,"Inductance": 4.7E-05,"Rated_Current": 2,"Resistance_DC": 0.04,"Size_Length": 0.015,"Size_Width": 0.007,"Size_Height": 0.0165,"Lines": "2","Temperature_AMB": 70,"Temperature_MAX": 125,"Voltage_Insulation": 1500,"Assembling_Technology": "THT","VDE": "VDE_WE-CMB-CMBH-CMBHC-CMBNiZn"},{"ID": 440365,"Series": "WE-CMB NiZn","Size": "XS","Order_Code": "744841210","Is_Internal": false,"Rated_Voltage": 250,"Inductance": 0.0001,"Rated_Current": 1.5,"Resistance_DC": 0.08,"Size_Length": 0.015,"Size_Width": 0.007,"Size_Height": 0.0165,"Lines": "2","Temperature_AMB": 70,"Temperature_MAX": 125,"Voltage_Insulation": 1500,"Assembling_Technology": "THT","VDE": "VDE_WE-CMB-CMBH-CMBHC-CMBNiZn"},{"ID": 440366,"Series": "WE-CMB NiZn","Size": "S","Order_Code": "7448421016","Is_Internal": false,"Rated_Voltage": 250,"Inductance": 1.6E-05,"Rated_Current": 10,"Resistance_DC": 0.0027,"Size_Length": 0.018,"Size_Width": 0.014,"Size_Height": 0.021,"Lines": "2","Temperature_AMB": 70,"Temperature_MAX": 125,"Voltage_Insulation": 1500,"Assembling_Technology": "THT","VDE": "VDE_WE-CMB-CMBH-CMBHC-CMBNiZn"},{"ID": 440367,"Series": "WE-CMB NiZn","Size": "S","Order_Code": "744842742","Is_Internal": false,"Rated_Voltage": 250,"Inductance": 4.2E-05,"Rated_Current": 6.5,"Resistance_DC": 0.0081,"Size_Length": 0.018,"Size_Width": 0.014,"Size_Height": 0.021,"Lines": "2","Temperature_AMB": 70,"Temperature_MAX": 125,"Voltage_Insulation": 1500,"Assembling_Technology": "THT","VDE": "VDE_WE-CMB-CMBH-CMBHC-CMBNiZn"},{"ID": 440368,"Series": "WE-CMB NiZn","Size": "S","Order_Code": "744842932","Is_Internal": false,"Rated_Voltage": 250,"Inductance": 3.2E-05,"Rated_Current": 8.5,"Resistance_DC": 0.0055,"Size_Length": 0.018,"Size_Width": 0.014,"Size_Height": 0.021,"Lines": "2","Temperature_AMB": 70,"Temperature_MAX": 125,"Voltage_Insulation": 1500,"Assembling_Technology": "THT","VDE": "VDE_WE-CMB-CMBH-CMBHC-CMBNiZn"},{"ID": 440369,"Series": "WE-CMB NiZn","Size": "S","Order_Code": "744842565","Is_Internal": false,"Rated_Voltage": 250,"Inductance": 6.5E-05,"Rated_Current": 5,"Resistance_DC": 0.013,"Size_Length": 0.018,"Size_Width": 0.014,"Size_Height": 0.021,"Lines": "2","Temperature_AMB": 70,"Temperature_MAX": 125,"Voltage_Insulation": 1500,"Assembling_Technology": "THT","VDE": "VDE_WE-CMB-CMBH-CMBHC-CMBNiZn"},{"ID": 440370,"Series": "WE-CMB NiZn","Size": "S","Order_Code": "744842311","Is_Internal": false,"Rated_Voltage": 250,"Inductance": 0.00011,"Rated_Current": 3,"Resistance_DC": 0.031,"Size_Length": 0.018,"Size_Width": 0.014,"Size_Height": 0.021,"Lines": "2","Temperature_AMB": 70,"Temperature_MAX": 125,"Voltage_Insulation": 1500,"Assembling_Technology": "THT","VDE": "VDE_WE-CMB-CMBH-CMBHC-CMBNiZn"},{"ID": 440371,"Series": "WE-ExB","Size": "L","Order_Code": "744844470","Is_Internal": false,"Rated_Voltage": 250,"Inductance": 4.7E-05,"Rated_Current": 15,"Resistance_DC": 0.0046,"Size_Length": 0.028,"Size_Width": 0.0185,"Size_Height": 0.033,"Lines": "2","Temperature_AMB": 70,"Temperature_MAX": 125,"Voltage_Insulation": 1500,"Assembling_Technology": "THT","VDE": ""},{"ID": 440372,"Series": "WE-ExB","Size": "L","Order_Code": "744844101","Is_Internal": false,"Rated_Voltage": 250,"Inductance": 0.0001,"Rated_Current": 14,"Resistance_DC": 0.006,"Size_Length": 0.028,"Size_Width": 0.0185,"Size_Height": 0.033,"Lines": "2","Temperature_AMB": 70,"Temperature_MAX": 125,"Voltage_Insulation": 1500,"Assembling_Technology": "THT","VDE": ""},{"ID": 440373,"Series": "WE-ExB","Size": "L","Order_Code": "744844221","Is_Internal": false,"Rated_Voltage": 250,"Inductance": 0.00022,"Rated_Current": 12,"Resistance_DC": 0.009,"Size_Length": 0.028,"Size_Width": 0.0185,"Size_Height": 0.033,"Lines": "2","Temperature_AMB": 70,"Temperature_MAX": 125,"Voltage_Insulation": 1500,"Assembling_Technology": "THT","VDE": ""},{"ID": 440374,"Series": "WE-ExB","Size": "L","Order_Code": "744844471","Is_Internal": false,"Rated_Voltage": 250,"Inductance": 0.00047,"Rated_Current": 9,"Resistance_DC": 0.016,"Size_Length": 0.028,"Size_Width": 0.0185,"Size_Height": 0.033,"Lines": "2","Temperature_AMB": 70,"Temperature_MAX": 125,"Voltage_Insulation": 1500,"Assembling_Technology": "THT","VDE": ""},{"ID": 440375,"Series": "WE-ExB","Size": "L","Order_Code": "744844102","Is_Internal": false,"Rated_Voltage": 250,"Inductance": 0.001,"Rated_Current": 4.5,"Resistance_DC": 0.042,"Size_Length": 0.028,"Size_Width": 0.0185,"Size_Height": 0.033,"Lines": "2","Temperature_AMB": 70,"Temperature_MAX": 125,"Voltage_Insulation": 1500,"Assembling_Technology": "THT","VDE": ""},{"ID": 440376,"Series": "WE-LF","Size": "SV","Order_Code": "74461240004","Is_Internal": false,"Rated_Voltage": 250,"Inductance": 0.0004,"Rated_Current": 3.6,"Resistance_DC": 0.02,"Size_Length": 0.018,"Size_Width": 0.013,"Size_Height": 0.02,"Lines": "2","Temperature_AMB": 70,"Temperature_MAX": 125,"Voltage_Insulation": 1500,"Assembling_Technology": "THT","VDE": "VDE_WE-LF_Vertical"},{"ID": 440377,"Series": "WE-LF","Size": "SV","Order_Code": "7446122001","Is_Internal": false,"Rated_Voltage": 250,"Inductance": 0.001,"Rated_Current": 2,"Resistance_DC": 0.06,"Size_Length": 0.018,"Size_Width": 0.013,"Size_Height": 0.02,"Lines": "2","Temperature_AMB": 70,"Temperature_MAX": 125,"Voltage_Insulation": 1500,"Assembling_Technology": "THT","VDE": "VDE_WE-LF_Vertical"},{"ID": 440378,"Series": "WE-LF","Size": "SV","Order_Code": "7446122003","Is_Internal": false,"Rated_Voltage": 250,"Inductance": 0.0033,"Rated_Current": 1.5,"Resistance_DC": 0.15,"Size_Length": 0.018,"Size_Width": 0.013,"Size_Height": 0.02,"Lines": "2","Temperature_AMB": 70,"Temperature_MAX": 125,"Voltage_Insulation": 1500,"Assembling_Technology": "THT","VDE": "VDE_WE-LF_Vertical"},{"ID": 440379,"Series": "WE-LF","Size": "SV","Order_Code": "7446121007","Is_Internal": false,"Rated_Voltage": 250,"Inductance": 0.0068,"Rated_Current": 1,"Resistance_DC": 0.3,"Size_Length": 0.018,"Size_Width": 0.013,"Size_Height": 0.02,"Lines": "2","Temperature_AMB": 70,"Temperature_MAX": 125,"Voltage_Insulation": 1500,"Assembling_Technology": "THT","VDE": "VDE_WE-LF_Vertical"},{"ID": 440380,"Series": "WE-LF","Size": "SV","Order_Code": "7446121010","Is_Internal": false,"Rated_Voltage": 250,"Inductance": 0.01,"Rated_Current": 0.7,"Resistance_DC": 0.55,"Size_Length": 0.018,"Size_Width": 0.013,"Size_Height": 0.02,"Lines": "2","Temperature_AMB": 70,"Temperature_MAX": 125,"Voltage_Insulation": 1500,"Assembling_Technology": "THT","VDE": "VDE_WE-LF_Vertical"},{"ID": 440381,"Series": "WE-LF","Size": "SV","Order_Code": "7446121018","Is_Internal": false,"Rated_Voltage": 250,"Inductance": 0.018,"Rated_Current": 0.5,"Resistance_DC": 0.75,"Size_Length": 0.018,"Size_Width": 0.013,"Size_Height": 0.02,"Lines": "2","Temperature_AMB": 70,"Temperature_MAX": 125,"Voltage_Insulation": 1500,"Assembling_Technology": "THT","VDE": "VDE_WE-LF_Vertical"},{"ID": 440382,"Series": "WE-LF","Size": "SV","Order_Code": "7446120027","Is_Internal": false,"Rated_Voltage": 250,"Inductance": 0.027,"Rated_Current": 0.4,"Resistance_DC": 1.2,"Size_Length": 0.018,"Size_Width": 0.013,"Size_Height": 0.02,"Lines": "2","Temperature_AMB": 70,"Temperature_MAX": 125,"Voltage_Insulation": 1500,"Assembling_Technology": "THT","VDE": "VDE_WE-LF_Vertical"},{"ID": 440383,"Series": "WE-LF","Size": "SV","Order_Code": "7446120039","Is_Internal": false,"Rated_Voltage": 250,"Inductance": 0.039,"Rated_Current": 0.4,"Resistance_DC": 1.7,"Size_Length": 0.018,"Size_Width": 0.013,"Size_Height": 0.02,"Lines": "2","Temperature_AMB": 70,"Temperature_MAX": 125,"Voltage_Insulation": 1500,"Assembling_Technology": "THT","VDE": "VDE_WE-LF_Vertical"},{"ID": 440384,"Series": "WE-LF","Size": "SV","Order_Code": "7446120047","Is_Internal": false,"Rated_Voltage": 250,"Inductance": 0.047,"Rated_Current": 0.3,"Resistance_DC": 2.6,"Size_Length": 0.018,"Size_Width": 0.013,"Size_Height": 0.02,"Lines": "2","Temperature_AMB": 70,"Temperature_MAX": 125,"Voltage_Insulation": 1500,"Assembling_Technology": "THT","VDE": "VDE_WE-LF_Vertical"},{"ID": 440385,"Series": "WE-LF","Size": "MV","Order_Code": "74462250007","Is_Internal": false,"Rated_Voltage": 250,"Inductance": 0.0007,"Rated_Current": 4.7,"Resistance_DC": 0.02,"Size_Length": 0.023,"Size_Width": 0.012,"Size_Height": 0.025,"Lines": "2","Temperature_AMB": 70,"Temperature_MAX": 125,"Voltage_Insulation": 1500,"Assembling_Technology": "THT","VDE": "VDE_WE-LF_Vertical"},{"ID": 440386,"Series": "WE-LF","Size": "MV","Order_Code": "7446223001","Is_Internal": false,"Rated_Voltage": 250,"Inductance": 0.001,"Rated_Current": 3,"Resistance_DC": 0.04,"Size_Length": 0.023,"Size_Width": 0.012,"Size_Height": 0.025,"Lines": "2","Temperature_AMB": 70,"Temperature_MAX": 125,"Voltage_Insulation": 1500,"Assembling_Technology": "THT","VDE": "VDE_WE-LF_Vertical"},{"ID": 440387,"Series": "WE-LF","Size": "MV","Order_Code": "7446222002","Is_Internal": false,"Rated_Voltage": 250,"Inductance": 0.0022,"Rated_Current": 2,"Resistance_DC": 0.06,"Size_Length": 0.023,"Size_Width": 0.012,"Size_Height": 0.025,"Lines": "2","Temperature_AMB": 70,"Temperature_MAX": 125,"Voltage_Insulation": 1500,"Assembling_Technology": "THT","VDE": "VDE_WE-LF_Vertical"},{"ID": 440388,"Series": "WE-LF","Size": "MV","Order_Code": "7446222003","Is_Internal": false,"Rated_Voltage": 250,"Inductance": 0.0033,"Rated_Current": 2,"Resistance_DC": 0.075,"Size_Length": 0.023,"Size_Width": 0.012,"Size_Height": 0.025,"Lines": "2","Temperature_AMB": 70,"Temperature_MAX": 125,"Voltage_Insulation": 1500,"Assembling_Technology": "THT","VDE": "VDE_WE-LF_Vertical"},{"ID": 440389,"Series": "WE-LF","Size": "MV","Order_Code": "7446222004","Is_Internal": false,"Rated_Voltage": 250,"Inductance": 0.0042,"Rated_Current": 2,"Resistance_DC": 0.12,"Size_Length": 0.023,"Size_Width": 0.012,"Size_Height": 0.025,"Lines": "2","Temperature_AMB": 70,"Temperature_MAX": 125,"Voltage_Insulation": 1500,"Assembling_Technology": "THT","VDE": "VDE_WE-LF_Vertical"},{"ID": 440390,"Series": "WE-LF","Size": "MV","Order_Code": "7446222007","Is_Internal": false,"Rated_Voltage": 250,"Inductance": 0.0068,"Rated_Current": 1.5,"Resistance_DC": 0.2,"Size_Length": 0.023,"Size_Width": 0.012,"Size_Height": 0.025,"Lines": "2","Temperature_AMB": 70,"Temperature_MAX": 125,"Voltage_Insulation": 1500,"Assembling_Technology": "THT","VDE": "VDE_WE-LF_Vertical"},{"ID": 440391,"Series": "WE-LF","Size": "MV","Order_Code": "7446221010","Is_Internal": false,"Rated_Voltage": 250,"Inductance": 0.01,"Rated_Current": 1.3,"Resistance_DC": 0.25,"Size_Length": 0.023,"Size_Width": 0.012,"Size_Height": 0.025,"Lines": "2","Temperature_AMB": 70,"Temperature_MAX": 125,"Voltage_Insulation": 1500,"Assembling_Technology": "THT","VDE": "VDE_WE-LF_Vertical"},{"ID": 440392,"Series": "WE-LF","Size": "MV","Order_Code": "7446221012","Is_Internal": false,"Rated_Voltage": 250,"Inductance": 0.012,"Rated_Current": 1.2,"Resistance_DC": 0.28,"Size_Length": 0.023,"Size_Width": 0.012,"Size_Height": 0.025,"Lines": "2","Temperature_AMB": 70,"Temperature_MAX": 125,"Voltage_Insulation": 1500,"Assembling_Technology": "THT","VDE": "VDE_WE-LF_Vertical"},{"ID": 440393,"Series": "WE-LF","Size": "MV","Order_Code": "7446221027","Is_Internal": false,"Rated_Voltage": 250,"Inductance": 0.027,"Rated_Current": 0.6,"Resistance_DC": 0.7,"Size_Length": 0.023,"Size_Width": 0.012,"Size_Height": 0.025,"Lines": "2","Temperature_AMB": 70,"Temperature_MAX": 125,"Voltage_Insulation": 1500,"Assembling_Technology": "THT","VDE": "VDE_WE-LF_Vertical"},{"ID": 440394,"Series": "WE-LF","Size": "MV","Order_Code": "7446220047","Is_Internal": false,"Rated_Voltage": 250,"Inductance": 0.047,"Rated_Current": 0.4,"Resistance_DC": 1.6,"Size_Length": 0.023,"Size_Width": 0.012,"Size_Height": 0.025,"Lines": "2","Temperature_AMB": 70,"Temperature_MAX": 125,"Voltage_Insulation": 1500,"Assembling_Technology": "THT","VDE": "VDE_WE-LF_Vertical"},{"ID": 440395,"Series": "WE-LF","Size": "LV","Order_Code": "7446326002","Is_Internal": false,"Rated_Voltage": 250,"Inductance": 0.0018,"Rated_Current": 6,"Resistance_DC": 0.023,"Size_Length": 0.026,"Size_Width": 0.014,"Size_Height": 0.03,"Lines": "2","Temperature_AMB": 70,"Temperature_MAX": 125,"Voltage_Insulation": 1500,"Assembling_Technology": "THT","VDE": "VDE_WE-LF_Vertical"},{"ID": 440396,"Series": "WE-LF","Size": "LV","Order_Code": "7446323003","Is_Internal": false,"Rated_Voltage": 250,"Inductance": 0.0027,"Rated_Current": 3,"Resistance_DC": 0.06,"Size_Length": 0.026,"Size_Width": 0.014,"Size_Height": 0.03,"Lines": "2","Temperature_AMB": 70,"Temperature_MAX": 125,"Voltage_Insulation": 1500,"Assembling_Technology": "THT","VDE": "VDE_WE-LF_Vertical"},{"ID": 440397,"Series": "WE-LF","Size": "LV","Order_Code": "7446323004","Is_Internal": false,"Rated_Voltage": 250,"Inductance": 0.004,"Rated_Current": 3,"Resistance_DC": 0.07,"Size_Length": 0.026,"Size_Width": 0.014,"Size_Height": 0.03,"Lines": "2","Temperature_AMB": 70,"Temperature_MAX": 125,"Voltage_Insulation": 1500,"Assembling_Technology": "THT","VDE": "VDE_WE-LF_Vertical"},{"ID": 440398,"Series": "WE-LF","Size": "LV","Order_Code": "7446322007","Is_Internal": false,"Rated_Voltage": 250,"Inductance": 0.0068,"Rated_Current": 1.9,"Resistance_DC": 0.16,"Size_Length": 0.026,"Size_Width": 0.014,"Size_Height": 0.03,"Lines": "2","Temperature_AMB": 70,"Temperature_MAX": 125,"Voltage_Insulation": 1500,"Assembling_Technology": "THT","VDE": "VDE_WE-LF_Vertical"},{"ID": 440399,"Series": "WE-LF","Size": "LV","Order_Code": "7446322010","Is_Internal": false,"Rated_Voltage": 250,"Inductance": 0.01,"Rated_Current": 1.9,"Resistance_DC": 0.18,"Size_Length": 0.026,"Size_Width": 0.014,"Size_Height": 0.03,"Lines": "2","Temperature_AMB": 70,"Temperature_MAX": 125,"Voltage_Insulation": 1500,"Assembling_Technology": "THT","VDE": "VDE_WE-LF_Vertical"},{"ID": 440400,"Series": "WE-LF","Size": "LV","Order_Code": "7446321027","Is_Internal": false,"Rated_Voltage": 250,"Inductance": 0.027,"Rated_Current": 1,"Resistance_DC": 0.64,"Size_Length": 0.026,"Size_Width": 0.014,"Size_Height": 0.03,"Lines": "2","Temperature_AMB": 70,"Temperature_MAX": 125,"Voltage_Insulation": 1500,"Assembling_Technology": "THT","VDE": "VDE_WE-LF_Vertical"},{"ID": 440401,"Series": "WE-LF","Size": "LV","Order_Code": "7446321033","Is_Internal": false,"Rated_Voltage": 250,"Inductance": 0.033,"Rated_Current": 0.8,"Resistance_DC": 0.85,"Size_Length": 0.026,"Size_Width": 0.014,"Size_Height": 0.03,"Lines": "2","Temperature_AMB": 70,"Temperature_MAX": 125,"Voltage_Insulation": 1500,"Assembling_Technology": "THT","VDE": "VDE_WE-LF_Vertical"},{"ID": 440402,"Series": "WE-LF","Size": "LV","Order_Code": "7446321050","Is_Internal": false,"Rated_Voltage": 250,"Inductance": 0.05,"Rated_Current": 0.6,"Resistance_DC": 1.2,"Size_Length": 0.026,"Size_Width": 0.014,"Size_Height": 0.03,"Lines": "2","Temperature_AMB": 70,"Temperature_MAX": 125,"Voltage_Insulation": 1500,"Assembling_Technology": "THT","VDE": "VDE_WE-LF_Vertical"},{"ID": 440403,"Series": "WE-LF","Size": "XV","Order_Code": "7446424002","Is_Internal": false,"Rated_Voltage": 250,"Inductance": 0.0022,"Rated_Current": 4.3,"Resistance_DC": 0.038,"Size_Length": 0.032,"Size_Width": 0.017,"Size_Height": 0.035,"Lines": "2","Temperature_AMB": 70,"Temperature_MAX": 125,"Voltage_Insulation": 1500,"Assembling_Technology": "THT","VDE": "VDE_WE-LF_Vertical"},{"ID": 440404,"Series": "WE-LF","Size": "XV","Order_Code": "7446424003","Is_Internal": false,"Rated_Voltage": 250,"Inductance": 0.0033,"Rated_Current": 4,"Resistance_DC": 0.065,"Size_Length": 0.032,"Size_Width": 0.017,"Size_Height": 0.035,"Lines": "2","Temperature_AMB": 70,"Temperature_MAX": 125,"Voltage_Insulation": 1500,"Assembling_Technology": "THT","VDE": "VDE_WE-LF_Vertical"},{"ID": 440405,"Series": "WE-LF","Size": "XV","Order_Code": "7446422007","Is_Internal": false,"Rated_Voltage": 250,"Inductance": 0.0068,"Rated_Current": 2.5,"Resistance_DC": 0.12,"Size_Length": 0.032,"Size_Width": 0.017,"Size_Height": 0.035,"Lines": "2","Temperature_AMB": 70,"Temperature_MAX": 125,"Voltage_Insulation": 1500,"Assembling_Technology": "THT","VDE": "VDE_WE-LF_Vertical"},{"ID": 440406,"Series": "WE-LF","Size": "SH","Order_Code": "74466240007","Is_Internal": false,"Rated_Voltage": 250,"Inductance": 0.0007,"Rated_Current": 4,"Resistance_DC": 0.0247,"Size_Length": 0.017,"Size_Width": 0.017,"Size_Height": 0.012,"Lines": "2","Temperature_AMB": 70,"Temperature_MAX": 125,"Voltage_Insulation": 1500,"Assembling_Technology": "THT","VDE": "VDE_WE-LF_Horizontal"},{"ID": 440407,"Series": "WE-LF","Size": "SH","Order_Code": "7446622001","Is_Internal": false,"Rated_Voltage": 250,"Inductance": 0.001,"Rated_Current": 2,"Resistance_DC": 0.06,"Size_Length": 0.017,"Size_Width": 0.017,"Size_Height": 0.012,"Lines": "2","Temperature_AMB": 70,"Temperature_MAX": 125,"Voltage_Insulation": 1500,"Assembling_Technology": "THT","VDE": "VDE_WE-LF_Horizontal"},{"ID": 440408,"Series": "WE-LF","Size": "SH","Order_Code": "7446622002","Is_Internal": false,"Rated_Voltage": 250,"Inductance": 0.0022,"Rated_Current": 2,"Resistance_DC": 0.1,"Size_Length": 0.017,"Size_Width": 0.017,"Size_Height": 0.012,"Lines": "2","Temperature_AMB": 70,"Temperature_MAX": 125,"Voltage_Insulation": 1500,"Assembling_Technology": "THT","VDE": "VDE_WE-LF_Horizontal"},{"ID": 440409,"Series": "WE-LF","Size": "SH","Order_Code": "7446622003","Is_Internal": false,"Rated_Voltage": 250,"Inductance": 0.0033,"Rated_Current": 1.5,"Resistance_DC": 0.15,"Size_Length": 0.017,"Size_Width": 0.017,"Size_Height": 0.012,"Lines": "2","Temperature_AMB": 70,"Temperature_MAX": 125,"Voltage_Insulation": 1500,"Assembling_Technology": "THT","VDE": "VDE_WE-LF_Horizontal"},{"ID": 440410,"Series": "WE-LF","Size": "SH","Order_Code": "7446621007","Is_Internal": false,"Rated_Voltage": 250,"Inductance": 0.0068,"Rated_Current": 1,"Resistance_DC": 0.3,"Size_Length": 0.017,"Size_Width": 0.017,"Size_Height": 0.012,"Lines": "2","Temperature_AMB": 70,"Temperature_MAX": 125,"Voltage_Insulation": 1500,"Assembling_Technology": "THT","VDE": "VDE_WE-LF_Horizontal"},{"ID": 440411,"Series": "WE-LF","Size": "SH","Order_Code": "7446621010","Is_Internal": false,"Rated_Voltage": 250,"Inductance": 0.01,"Rated_Current": 0.7,"Resistance_DC": 0.55,"Size_Length": 0.017,"Size_Width": 0.017,"Size_Height": 0.012,"Lines": "2","Temperature_AMB": 70,"Temperature_MAX": 125,"Voltage_Insulation": 1500,"Assembling_Technology": "THT","VDE": "VDE_WE-LF_Horizontal"},{"ID": 440412,"Series": "WE-LF","Size": "SH","Order_Code": "7446620015","Is_Internal": false,"Rated_Voltage": 250,"Inductance": 0.015,"Rated_Current": 0.5,"Resistance_DC": 0.83,"Size_Length": 0.017,"Size_Width": 0.017,"Size_Height": 0.012,"Lines": "2","Temperature_AMB": 70,"Temperature_MAX": 125,"Voltage_Insulation": 1500,"Assembling_Technology": "THT","VDE": "VDE_WE-LF_Horizontal"},{"ID": 440413,"Series": "WE-LF","Size": "SH","Order_Code": "7446620027","Is_Internal": false,"Rated_Voltage": 250,"Inductance": 0.027,"Rated_Current": 0.4,"Resistance_DC": 1.2,"Size_Length": 0.017,"Size_Width": 0.017,"Size_Height": 0.012,"Lines": "2","Temperature_AMB": 70,"Temperature_MAX": 125,"Voltage_Insulation": 1500,"Assembling_Technology": "THT","VDE": "VDE_WE-LF_Horizontal"},{"ID": 440414,"Series": "WE-LF","Size": "SH","Order_Code": "7446620039","Is_Internal": false,"Rated_Voltage": 250,"Inductance": 0.039,"Rated_Current": 0.4,"Resistance_DC": 1.7,"Size_Length": 0.017,"Size_Width": 0.017,"Size_Height": 0.012,"Lines": "2","Temperature_AMB": 70,"Temperature_MAX": 125,"Voltage_Insulation": 1500,"Assembling_Technology": "THT","VDE": "VDE_WE-LF_Horizontal"},{"ID": 440415,"Series": "WE-LF","Size": "MH","Order_Code": "7446723001","Is_Internal": false,"Rated_Voltage": 250,"Inductance": 0.0012,"Rated_Current": 3,"Resistance_DC": 0.04,"Size_Length": 0.022,"Size_Width": 0.022,"Size_Height": 0.014,"Lines": "2","Temperature_AMB": 70,"Temperature_MAX": 125,"Voltage_Insulation": 1500,"Assembling_Technology": "THT","VDE": "VDE_WE-LF_Horizontal"},{"ID": 440416,"Series": "WE-LF","Size": "MH","Order_Code": "7446722002","Is_Internal": false,"Rated_Voltage": 250,"Inductance": 0.0022,"Rated_Current": 2,"Resistance_DC": 0.06,"Size_Length": 0.022,"Size_Width": 0.022,"Size_Height": 0.014,"Lines": "2","Temperature_AMB": 70,"Temperature_MAX": 125,"Voltage_Insulation": 1500,"Assembling_Technology": "THT","VDE": "VDE_WE-LF_Horizontal"},{"ID": 440417,"Series": "WE-LF","Size": "MH","Order_Code": "7446722004","Is_Internal": false,"Rated_Voltage": 250,"Inductance": 0.0042,"Rated_Current": 1.9,"Resistance_DC": 0.12,"Size_Length": 0.022,"Size_Width": 0.022,"Size_Height": 0.014,"Lines": "2","Temperature_AMB": 70,"Temperature_MAX": 125,"Voltage_Insulation": 1500,"Assembling_Technology": "THT","VDE": "VDE_WE-LF_Horizontal"},{"ID": 440418,"Series": "WE-LF","Size": "MH","Order_Code": "7446722007","Is_Internal": false,"Rated_Voltage": 250,"Inductance": 0.0068,"Rated_Current": 1.5,"Resistance_DC": 0.2,"Size_Length": 0.022,"Size_Width": 0.022,"Size_Height": 0.014,"Lines": "2","Temperature_AMB": 70,"Temperature_MAX": 125,"Voltage_Insulation": 1500,"Assembling_Technology": "THT","VDE": "VDE_WE-LF_Horizontal"},{"ID": 440419,"Series": "WE-LF","Size": "MH","Order_Code": "7446721010","Is_Internal": false,"Rated_Voltage": 250,"Inductance": 0.01,"Rated_Current": 1.3,"Resistance_DC": 0.25,"Size_Length": 0.022,"Size_Width": 0.022,"Size_Height": 0.014,"Lines": "2","Temperature_AMB": 70,"Temperature_MAX": 125,"Voltage_Insulation": 1500,"Assembling_Technology": "THT","VDE": "VDE_WE-LF_Horizontal"},{"ID": 440420,"Series": "WE-LF","Size": "MH","Order_Code": "7446721027","Is_Internal": false,"Rated_Voltage": 250,"Inductance": 0.027,"Rated_Current": 0.6,"Resistance_DC": 0.7,"Size_Length": 0.022,"Size_Width": 0.022,"Size_Height": 0.014,"Lines": "2","Temperature_AMB": 70,"Temperature_MAX": 125,"Voltage_Insulation": 1500,"Assembling_Technology": "THT","VDE": "VDE_WE-LF_Horizontal"},{"ID": 440421,"Series": "WE-LF","Size": "MH","Order_Code": "7446720047","Is_Internal": false,"Rated_Voltage": 250,"Inductance": 0.047,"Rated_Current": 0.4,"Resistance_DC": 1.6,"Size_Length": 0.022,"Size_Width": 0.022,"Size_Height": 0.014,"Lines": "2","Temperature_AMB": 70,"Temperature_MAX": 125,"Voltage_Insulation": 1500,"Assembling_Technology": "THT","VDE": "VDE_WE-LF_Horizontal"},{"ID": 440422,"Series": "WE-LF","Size": "LH","Order_Code": "7446823003","Is_Internal": false,"Rated_Voltage": 250,"Inductance": 0.0027,"Rated_Current": 3,"Resistance_DC": 0.06,"Size_Length": 0.028,"Size_Width": 0.028,"Size_Height": 0.016,"Lines": "2","Temperature_AMB": 70,"Temperature_MAX": 125,"Voltage_Insulation": 1500,"Assembling_Technology": "THT","VDE": "VDE_WE-LF_Horizontal"},{"ID": 440423,"Series": "WE-LF","Size": "LH","Order_Code": "7446822006","Is_Internal": false,"Rated_Voltage": 250,"Inductance": 0.0056,"Rated_Current": 2,"Resistance_DC": 0.16,"Size_Length": 0.028,"Size_Width": 0.028,"Size_Height": 0.016,"Lines": "2","Temperature_AMB": 70,"Temperature_MAX": 125,"Voltage_Insulation": 1500,"Assembling_Technology": "THT","VDE": "VDE_WE-LF_Horizontal"},{"ID": 440424,"Series": "WE-LF","Size": "LH","Order_Code": "7446823006","Is_Internal": false,"Rated_Voltage": 250,"Inductance": 0.0056,"Rated_Current": 2.4,"Resistance_DC": 0.1,"Size_Length": 0.028,"Size_Width": 0.028,"Size_Height": 0.016,"Lines": "2","Temperature_AMB": 70,"Temperature_MAX": 125,"Voltage_Insulation": 1500,"Assembling_Technology": "THT","VDE": "VDE_WE-LF_Horizontal"},{"ID": 440425,"Series": "WE-LF","Size": "LH","Order_Code": "7446821027","Is_Internal": false,"Rated_Voltage": 250,"Inductance": 0.027,"Rated_Current": 1,"Resistance_DC": 0.64,"Size_Length": 0.028,"Size_Width": 0.028,"Size_Height": 0.016,"Lines": "2","Temperature_AMB": 70,"Temperature_MAX": 125,"Voltage_Insulation": 1500,"Assembling_Technology": "THT","VDE": "VDE_WE-LF_Horizontal"},{"ID": 440426,"Series": "WE-LF","Size": "XH","Order_Code": "7446926002","Is_Internal": false,"Rated_Voltage": 250,"Inductance": 0.0018,"Rated_Current": 6,"Resistance_DC": 0.03,"Size_Length": 0.033,"Size_Width": 0.033,"Size_Height": 0.019,"Lines": "2","Temperature_AMB": 70,"Temperature_MAX": 125,"Voltage_Insulation": 1500,"Assembling_Technology": "THT","VDE": "VDE_WE-LF_Horizontal"},{"ID": 440427,"Series": "WE-LF","Size": "XH","Order_Code": "7446924003","Is_Internal": false,"Rated_Voltage": 250,"Inductance": 0.0033,"Rated_Current": 4,"Resistance_DC": 0.065,"Size_Length": 0.033,"Size_Width": 0.033,"Size_Height": 0.019,"Lines": "2","Temperature_AMB": 70,"Temperature_MAX": 125,"Voltage_Insulation": 1500,"Assembling_Technology": "THT","VDE": "VDE_WE-LF_Horizontal"},{"ID": 440428,"Series": "WE-LF","Size": "XH","Order_Code": "7446923010","Is_Internal": false,"Rated_Voltage": 250,"Inductance": 0.01,"Rated_Current": 3,"Resistance_DC": 0.155,"Size_Length": 0.033,"Size_Width": 0.033,"Size_Height": 0.019,"Lines": "2","Temperature_AMB": 70,"Temperature_MAX": 125,"Voltage_Insulation": 1500,"Assembling_Technology": "THT","VDE": "VDE_WE-LF_Horizontal"},{"ID": 440429,"Series": "WE-LF","Size": "XH","Order_Code": "7446921027","Is_Internal": false,"Rated_Voltage": 250,"Inductance": 0.027,"Rated_Current": 1.2,"Resistance_DC": 0.4,"Size_Length": 0.033,"Size_Width": 0.033,"Size_Height": 0.019,"Lines": "2","Temperature_AMB": 70,"Temperature_MAX": 125,"Voltage_Insulation": 1500,"Assembling_Technology": "THT","VDE": "VDE_WE-LF_Horizontal"},{"ID": 440430,"Series": "WE-LF SMD","Size": "","Order_Code": "74466340007","Is_Internal": false,"Rated_Voltage": 250,"Inductance": 0.0007,"Rated_Current": 5.25,"Resistance_DC": 0.03,"Size_Length": 0.018,"Size_Width": 0.023,"Size_Height": 0.011,"Lines": "2","Temperature_AMB": 70,"Temperature_MAX": 125,"Voltage_Insulation": 1500,"Assembling_Technology": "SMT","VDE": "VDE_WE-LFSMD"},{"ID": 440431,"Series": "WE-LF SMD","Size": "","Order_Code": "7446632001","Is_Internal": false,"Rated_Voltage": 250,"Inductance": 0.001,"Rated_Current": 3,"Resistance_DC": 0.06,"Size_Length": 0.018,"Size_Width": 0.023,"Size_Height": 0.011,"Lines": "2","Temperature_AMB": 70,"Temperature_MAX": 125,"Voltage_Insulation": 1500,"Assembling_Technology": "SMT","VDE": "VDE_WE-LFSMD"},{"ID": 440432,"Series": "WE-LF SMD","Size": "","Order_Code": "7446632002","Is_Internal": false,"Rated_Voltage": 250,"Inductance": 0.0022,"Rated_Current": 2.75,"Resistance_DC": 0.1,"Size_Length": 0.018,"Size_Width": 0.023,"Size_Height": 0.011,"Lines": "2","Temperature_AMB": 70,"Temperature_MAX": 125,"Voltage_Insulation": 1500,"Assembling_Technology": "SMT","VDE": "VDE_WE-LFSMD"},{"ID": 440433,"Series": "WE-LF SMD","Size": "","Order_Code": "7446632003","Is_Internal": false,"Rated_Voltage": 250,"Inductance": 0.0033,"Rated_Current": 2.25,"Resistance_DC": 0.15,"Size_Length": 0.018,"Size_Width": 0.023,"Size_Height": 0.011,"Lines": "2","Temperature_AMB": 70,"Temperature_MAX": 125,"Voltage_Insulation": 1500,"Assembling_Technology": "SMT","VDE": "VDE_WE-LFSMD"},{"ID": 440434,"Series": "WE-LF SMD","Size": "","Order_Code": "7446631007","Is_Internal": false,"Rated_Voltage": 250,"Inductance": 0.0068,"Rated_Current": 1.4,"Resistance_DC": 0.3,"Size_Length": 0.018,"Size_Width": 0.023,"Size_Height": 0.011,"Lines": "2","Temperature_AMB": 70,"Temperature_MAX": 125,"Voltage_Insulation": 1500,"Assembling_Technology": "SMT","VDE": "VDE_WE-LFSMD"},{"ID": 440435,"Series": "WE-LF SMD","Size": "","Order_Code": "7446631010","Is_Internal": false,"Rated_Voltage": 250,"Inductance": 0.01,"Rated_Current": 1,"Resistance_DC": 0.55,"Size_Length": 0.018,"Size_Width": 0.023,"Size_Height": 0.011,"Lines": "2","Temperature_AMB": 70,"Temperature_MAX": 125,"Voltage_Insulation": 1500,"Assembling_Technology": "SMT","VDE": "VDE_WE-LFSMD"},{"ID": 440436,"Series": "WE-LF SMD","Size": "","Order_Code": "7446630027","Is_Internal": false,"Rated_Voltage": 250,"Inductance": 0.027,"Rated_Current": 0.6,"Resistance_DC": 1.2,"Size_Length": 0.018,"Size_Width": 0.023,"Size_Height": 0.011,"Lines": "2","Temperature_AMB": 70,"Temperature_MAX": 125,"Voltage_Insulation": 1500,"Assembling_Technology": "SMT","VDE": "VDE_WE-LFSMD"},{"ID": 440437,"Series": "WE-LF SMD","Size": "","Order_Code": "7446630039","Is_Internal": false,"Rated_Voltage": 250,"Inductance": 0.039,"Rated_Current": 0.55,"Resistance_DC": 1.7,"Size_Length": 0.018,"Size_Width": 0.023,"Size_Height": 0.011,"Lines": "2","Temperature_AMB": 70,"Temperature_MAX": 125,"Voltage_Insulation": 1500,"Assembling_Technology": "SMT","VDE": "VDE_WE-LFSMD"},{"ID": 440438,"Series": "WE-LF SMD","Size": "","Order_Code": "7446630047","Is_Internal": false,"Rated_Voltage": 250,"Inductance": 0.047,"Rated_Current": 0.4,"Resistance_DC": 2.6,"Size_Length": 0.018,"Size_Width": 0.023,"Size_Height": 0.011,"Lines": "2","Temperature_AMB": 70,"Temperature_MAX": 125,"Voltage_Insulation": 1500,"Assembling_Technology": "SMT","VDE": "VDE_WE-LFSMD"},{"ID": 440439,"Series": "WE-TFC","Size": "UT","Order_Code": "744862018","Is_Internal": false,"Rated_Voltage": 400,"Inductance": 0.0018,"Rated_Current": 1,"Resistance_DC": 0.31,"Size_Length": 0.017,"Size_Width": 0.011,"Size_Height": 0.017,"Lines": "2","Temperature_AMB": 70,"Temperature_MAX": 125,"Voltage_Insulation": 3000,"Assembling_Technology": "THT","VDE": ""},{"ID": 440440,"Series": "WE-TFC","Size": "UT","Order_Code": "744862033","Is_Internal": false,"Rated_Voltage": 400,"Inductance": 0.0033,"Rated_Current": 0.8,"Resistance_DC": 0.51,"Size_Length": 0.017,"Size_Width": 0.011,"Size_Height": 0.017,"Lines": "2","Temperature_AMB": 70,"Temperature_MAX": 125,"Voltage_Insulation": 3000,"Assembling_Technology": "THT","VDE": ""},{"ID": 440441,"Series": "WE-TFC","Size": "UT","Order_Code": "744862056","Is_Internal": false,"Rated_Voltage": 400,"Inductance": 0.0056,"Rated_Current": 0.6,"Resistance_DC": 0.83,"Size_Length": 0.017,"Size_Width": 0.011,"Size_Height": 0.017,"Lines": "2","Temperature_AMB": 70,"Temperature_MAX": 125,"Voltage_Insulation": 3000,"Assembling_Technology": "THT","VDE": ""},{"ID": 440442,"Series": "WE-TFC","Size": "UT","Order_Code": "744862082","Is_Internal": false,"Rated_Voltage": 400,"Inductance": 0.0082,"Rated_Current": 0.5,"Resistance_DC": 1.3,"Size_Length": 0.017,"Size_Width": 0.011,"Size_Height": 0.017,"Lines": "2","Temperature_AMB": 70,"Temperature_MAX": 125,"Voltage_Insulation": 3000,"Assembling_Technology": "THT","VDE": ""},{"ID": 440443,"Series": "WE-TFC","Size": "UT","Order_Code": "744862100","Is_Internal": false,"Rated_Voltage": 400,"Inductance": 0.01,"Rated_Current": 0.45,"Resistance_DC": 1.65,"Size_Length": 0.017,"Size_Width": 0.011,"Size_Height": 0.017,"Lines": "2","Temperature_AMB": 70,"Temperature_MAX": 125,"Voltage_Insulation": 3000,"Assembling_Technology": "THT","VDE": ""},{"ID": 440444,"Series": "WE-TFC","Size": "UT","Order_Code": "744862120","Is_Internal": false,"Rated_Voltage": 400,"Inductance": 0.012,"Rated_Current": 0.4,"Resistance_DC": 2,"Size_Length": 0.017,"Size_Width": 0.011,"Size_Height": 0.017,"Lines": "2","Temperature_AMB": 70,"Temperature_MAX": 125,"Voltage_Insulation": 3000,"Assembling_Technology": "THT","VDE": ""},{"ID": 440445,"Series": "WE-TFC","Size": "UT","Order_Code": "744862180","Is_Internal": false,"Rated_Voltage": 400,"Inductance": 0.018,"Rated_Current": 0.3,"Resistance_DC": 3.1,"Size_Length": 0.017,"Size_Width": 0.011,"Size_Height": 0.017,"Lines": "2","Temperature_AMB": 70,"Temperature_MAX": 125,"Voltage_Insulation": 3000,"Assembling_Technology": "THT","VDE": ""},{"ID": 440446,"Series": "WE-TFC","Size": "UT","Order_Code": "744862250","Is_Internal": false,"Rated_Voltage": 400,"Inductance": 0.025,"Rated_Current": 0.25,"Resistance_DC": 3.6,"Size_Length": 0.017,"Size_Width": 0.011,"Size_Height": 0.017,"Lines": "2","Temperature_AMB": 70,"Temperature_MAX": 125,"Voltage_Insulation": 3000,"Assembling_Technology": "THT","VDE": ""},{"ID": 440447,"Series": "WE-TFCH","Size": "UT","Order_Code": "744861018","Is_Internal": false,"Rated_Voltage": 400,"Inductance": 0.0018,"Rated_Current": 1,"Resistance_DC": 0.31,"Size_Length": 0.017,"Size_Width": 0.0155,"Size_Height": 0.0125,"Lines": "2","Temperature_AMB": 70,"Temperature_MAX": 125,"Voltage_Insulation": 3000,"Assembling_Technology": "THT","VDE": ""},{"ID": 440448,"Series": "WE-TFCH","Size": "UT","Order_Code": "744861033","Is_Internal": false,"Rated_Voltage": 400,"Inductance": 0.0033,"Rated_Current": 0.8,"Resistance_DC": 0.51,"Size_Length": 0.017,"Size_Width": 0.0155,"Size_Height": 0.0125,"Lines": "2","Temperature_AMB": 70,"Temperature_MAX": 125,"Voltage_Insulation": 3000,"Assembling_Technology": "THT","VDE": ""},{"ID": 440449,"Series": "WE-TFCH","Size": "UT","Order_Code": "744861056","Is_Internal": false,"Rated_Voltage": 400,"Inductance": 0.0056,"Rated_Current": 0.6,"Resistance_DC": 0.83,"Size_Length": 0.017,"Size_Width": 0.0155,"Size_Height": 0.0125,"Lines": "2","Temperature_AMB": 70,"Temperature_MAX": 125,"Voltage_Insulation": 3000,"Assembling_Technology": "THT","VDE": ""},{"ID": 440450,"Series": "WE-TFCH","Size": "UT","Order_Code": "744861082","Is_Internal": false,"Rated_Voltage": 400,"Inductance": 0.0082,"Rated_Current": 0.5,"Resistance_DC": 1.3,"Size_Length": 0.017,"Size_Width": 0.0155,"Size_Height": 0.0125,"Lines": "2","Temperature_AMB": 70,"Temperature_MAX": 125,"Voltage_Insulation": 3000,"Assembling_Technology": "THT","VDE": ""},{"ID": 440451,"Series": "WE-TFCH","Size": "UT","Order_Code": "744861100","Is_Internal": false,"Rated_Voltage": 400,"Inductance": 0.01,"Rated_Current": 0.45,"Resistance_DC": 1.65,"Size_Length": 0.017,"Size_Width": 0.0155,"Size_Height": 0.0125,"Lines": "2","Temperature_AMB": 70,"Temperature_MAX": 125,"Voltage_Insulation": 3000,"Assembling_Technology": "THT","VDE": ""},{"ID": 440452,"Series": "WE-TFCH","Size": "UT","Order_Code": "744861120","Is_Internal": false,"Rated_Voltage": 400,"Inductance": 0.012,"Rated_Current": 0.4,"Resistance_DC": 2,"Size_Length": 0.017,"Size_Width": 0.0155,"Size_Height": 0.0125,"Lines": "2","Temperature_AMB": 70,"Temperature_MAX": 125,"Voltage_Insulation": 3000,"Assembling_Technology": "THT","VDE": ""},{"ID": 440453,"Series": "WE-TFCH","Size": "UT","Order_Code": "744861180","Is_Internal": false,"Rated_Voltage": 400,"Inductance": 0.018,"Rated_Current": 0.3,"Resistance_DC": 3.1,"Size_Length": 0.017,"Size_Width": 0.0155,"Size_Height": 0.0125,"Lines": "2","Temperature_AMB": 70,"Temperature_MAX": 125,"Voltage_Insulation": 3000,"Assembling_Technology": "THT","VDE": ""},{"ID": 440454,"Series": "WE-TFCH","Size": "UT","Order_Code": "744861250","Is_Internal": false,"Rated_Voltage": 400,"Inductance": 0.025,"Rated_Current": 0.25,"Resistance_DC": 3.6,"Size_Length": 0.017,"Size_Width": 0.0155,"Size_Height": 0.0125,"Lines": "2","Temperature_AMB": 70,"Temperature_MAX": 125,"Voltage_Insulation": 3000,"Assembling_Technology": "THT","VDE": ""},{"ID": 440455,"Series": "WE-FC","Size": "ET","Order_Code": "7448640395","Is_Internal": false,"Rated_Voltage": 250,"Inductance": 0.00082,"Rated_Current": 2,"Resistance_DC": 0.07,"Size_Length": 0.0212,"Size_Width": 0.0212,"Size_Height": 0.0178,"Lines": "2","Temperature_AMB": 70,"Temperature_MAX": 125,"Voltage_Insulation": 2000,"Assembling_Technology": "THT","VDE": ""},{"ID": 440456,"Series": "WE-FC","Size": "ET","Order_Code": "7448640396","Is_Internal": false,"Rated_Voltage": 250,"Inductance": 0.0018,"Rated_Current": 1.5,"Resistance_DC": 0.15,"Size_Length": 0.0212,"Size_Width": 0.0212,"Size_Height": 0.0178,"Lines": "2","Temperature_AMB": 70,"Temperature_MAX": 125,"Voltage_Insulation": 2000,"Assembling_Technology": "THT","VDE": ""},{"ID": 440457,"Series": "WE-FC","Size": "ET","Order_Code": "7448640397","Is_Internal": false,"Rated_Voltage": 250,"Inductance": 0.0027,"Rated_Current": 1.2,"Resistance_DC": 0.225,"Size_Length": 0.0212,"Size_Width": 0.0212,"Size_Height": 0.0178,"Lines": "2","Temperature_AMB": 70,"Temperature_MAX": 125,"Voltage_Insulation": 2000,"Assembling_Technology": "THT","VDE": ""},{"ID": 440458,"Series": "WE-FC","Size": "ET","Order_Code": "7448640398","Is_Internal": false,"Rated_Voltage": 250,"Inductance": 0.0033,"Rated_Current": 1.1,"Resistance_DC": 0.25,"Size_Length": 0.0212,"Size_Width": 0.0212,"Size_Height": 0.0178,"Lines": "2","Temperature_AMB": 70,"Temperature_MAX": 125,"Voltage_Insulation": 2000,"Assembling_Technology": "THT","VDE": ""},{"ID": 440459,"Series": "WE-FC","Size": "ET","Order_Code": "7448640399","Is_Internal": false,"Rated_Voltage": 250,"Inductance": 0.0039,"Rated_Current": 1,"Resistance_DC": 0.28,"Size_Length": 0.0212,"Size_Width": 0.0212,"Size_Height": 0.0178,"Lines": "2","Temperature_AMB": 70,"Temperature_MAX": 125,"Voltage_Insulation": 2000,"Assembling_Technology": "THT","VDE": ""},{"ID": 440460,"Series": "WE-FC","Size": "ET","Order_Code": "7448640400","Is_Internal": false,"Rated_Voltage": 250,"Inductance": 0.0056,"Rated_Current": 0.8,"Resistance_DC": 0.4,"Size_Length": 0.0212,"Size_Width": 0.0212,"Size_Height": 0.0178,"Lines": "2","Temperature_AMB": 70,"Temperature_MAX": 125,"Voltage_Insulation": 2000,"Assembling_Technology": "THT","VDE": ""},{"ID": 440461,"Series": "WE-FC","Size": "ET","Order_Code": "7448640401","Is_Internal": false,"Rated_Voltage": 250,"Inductance": 0.0068,"Rated_Current": 0.8,"Resistance_DC": 0.48,"Size_Length": 0.0212,"Size_Width": 0.0212,"Size_Height": 0.0178,"Lines": "2","Temperature_AMB": 70,"Temperature_MAX": 125,"Voltage_Insulation": 2000,"Assembling_Technology": "THT","VDE": ""},{"ID": 440462,"Series": "WE-FC","Size": "ET","Order_Code": "7448640402","Is_Internal": false,"Rated_Voltage": 250,"Inductance": 0.01,"Rated_Current": 0.6,"Resistance_DC": 0.72,"Size_Length": 0.0212,"Size_Width": 0.0212,"Size_Height": 0.0178,"Lines": "2","Temperature_AMB": 70,"Temperature_MAX": 125,"Voltage_Insulation": 2000,"Assembling_Technology": "THT","VDE": ""},{"ID": 440463,"Series": "WE-FC","Size": "ET","Order_Code": "7448640403","Is_Internal": false,"Rated_Voltage": 250,"Inductance": 0.018,"Rated_Current": 0.5,"Resistance_DC": 1.17,"Size_Length": 0.0212,"Size_Width": 0.0212,"Size_Height": 0.0178,"Lines": "2","Temperature_AMB": 70,"Temperature_MAX": 125,"Voltage_Insulation": 2000,"Assembling_Technology": "THT","VDE": ""},{"ID": 440464,"Series": "WE-FC","Size": "ET","Order_Code": "7448640404","Is_Internal": false,"Rated_Voltage": 250,"Inductance": 0.022,"Rated_Current": 0.4,"Resistance_DC": 1.61,"Size_Length": 0.0212,"Size_Width": 0.0212,"Size_Height": 0.0178,"Lines": "2","Temperature_AMB": 70,"Temperature_MAX": 125,"Voltage_Insulation": 2000,"Assembling_Technology": "THT","VDE": ""},{"ID": 440465,"Series": "WE-FC","Size": "ET","Order_Code": "7448640405","Is_Internal": false,"Rated_Voltage": 250,"Inductance": 0.033,"Rated_Current": 0.3,"Resistance_DC": 2,"Size_Length": 0.0212,"Size_Width": 0.0212,"Size_Height": 0.0178,"Lines": "2","Temperature_AMB": 70,"Temperature_MAX": 125,"Voltage_Insulation": 2000,"Assembling_Technology": "THT","VDE": ""},{"ID": 440466,"Series": "WE-FC","Size": "UT","Order_Code": "7448640406","Is_Internal": false,"Rated_Voltage": 250,"Inductance": 0.00082,"Rated_Current": 2,"Resistance_DC": 0.07,"Size_Length": 0.0212,"Size_Width": 0.0166,"Size_Height": 0.0225,"Lines": "2","Temperature_AMB": 70,"Temperature_MAX": 125,"Voltage_Insulation": 2000,"Assembling_Technology": "THT","VDE": ""},{"ID": 440467,"Series": "WE-FC","Size": "UT","Order_Code": "7448640407","Is_Internal": false,"Rated_Voltage": 250,"Inductance": 0.0012,"Rated_Current": 1.6,"Resistance_DC": 0.1,"Size_Length": 0.0212,"Size_Width": 0.0166,"Size_Height": 0.0225,"Lines": "2","Temperature_AMB": 70,"Temperature_MAX": 125,"Voltage_Insulation": 2000,"Assembling_Technology": "THT","VDE": ""},{"ID": 440468,"Series": "WE-FC","Size": "UT","Order_Code": "7448640408","Is_Internal": false,"Rated_Voltage": 250,"Inductance": 0.0018,"Rated_Current": 1.5,"Resistance_DC": 0.12,"Size_Length": 0.0212,"Size_Width": 0.0166,"Size_Height": 0.0225,"Lines": "2","Temperature_AMB": 70,"Temperature_MAX": 125,"Voltage_Insulation": 2000,"Assembling_Technology": "THT","VDE": ""},{"ID": 440469,"Series": "WE-FC","Size": "UT","Order_Code": "7448640409","Is_Internal": false,"Rated_Voltage": 250,"Inductance": 0.0022,"Rated_Current": 1.3,"Resistance_DC": 0.17,"Size_Length": 0.0212,"Size_Width": 0.0166,"Size_Height": 0.0225,"Lines": "2","Temperature_AMB": 70,"Temperature_MAX": 125,"Voltage_Insulation": 2000,"Assembling_Technology": "THT","VDE": ""},{"ID": 440470,"Series": "WE-FC","Size": "UT","Order_Code": "7448640410","Is_Internal": false,"Rated_Voltage": 250,"Inductance": 0.0027,"Rated_Current": 1.2,"Resistance_DC": 0.19,"Size_Length": 0.0212,"Size_Width": 0.0166,"Size_Height": 0.0225,"Lines": "2","Temperature_AMB": 70,"Temperature_MAX": 125,"Voltage_Insulation": 2000,"Assembling_Technology": "THT","VDE": ""},{"ID": 440471,"Series": "WE-FC","Size": "UT","Order_Code": "7448640411","Is_Internal": false,"Rated_Voltage": 250,"Inductance": 0.0033,"Rated_Current": 1.2,"Resistance_DC": 0.21,"Size_Length": 0.0212,"Size_Width": 0.0166,"Size_Height": 0.0225,"Lines": "2","Temperature_AMB": 70,"Temperature_MAX": 125,"Voltage_Insulation": 2000,"Assembling_Technology": "THT","VDE": ""},{"ID": 440472,"Series": "WE-FC","Size": "UT","Order_Code": "7448640412","Is_Internal": false,"Rated_Voltage": 250,"Inductance": 0.0039,"Rated_Current": 1,"Resistance_DC": 0.27,"Size_Length": 0.0212,"Size_Width": 0.0166,"Size_Height": 0.0225,"Lines": "2","Temperature_AMB": 70,"Temperature_MAX": 125,"Voltage_Insulation": 2000,"Assembling_Technology": "THT","VDE": ""},{"ID": 440473,"Series": "WE-FC","Size": "UT","Order_Code": "7448640413","Is_Internal": false,"Rated_Voltage": 250,"Inductance": 0.0056,"Rated_Current": 0.8,"Resistance_DC": 0.415,"Size_Length": 0.0212,"Size_Width": 0.0166,"Size_Height": 0.0225,"Lines": "2","Temperature_AMB": 70,"Temperature_MAX": 125,"Voltage_Insulation": 2000,"Assembling_Technology": "THT","VDE": ""},{"ID": 440474,"Series": "WE-FC","Size": "UT","Order_Code": "7448640414","Is_Internal": false,"Rated_Voltage": 250,"Inductance": 0.0068,"Rated_Current": 0.7,"Resistance_DC": 0.467,"Size_Length": 0.0212,"Size_Width": 0.0166,"Size_Height": 0.0225,"Lines": "2","Temperature_AMB": 70,"Temperature_MAX": 125,"Voltage_Insulation": 2000,"Assembling_Technology": "THT","VDE": ""},{"ID": 440475,"Series": "WE-FC","Size": "UT","Order_Code": "7448640415","Is_Internal": false,"Rated_Voltage": 250,"Inductance": 0.01,"Rated_Current": 0.6,"Resistance_DC": 0.708,"Size_Length": 0.0212,"Size_Width": 0.0166,"Size_Height": 0.0225,"Lines": "2","Temperature_AMB": 70,"Temperature_MAX": 125,"Voltage_Insulation": 2000,"Assembling_Technology": "THT","VDE": ""},{"ID": 440476,"Series": "WE-FC","Size": "UT","Order_Code": "7448640416","Is_Internal": false,"Rated_Voltage": 250,"Inductance": 0.018,"Rated_Current": 0.5,"Resistance_DC": 1.635,"Size_Length": 0.0212,"Size_Width": 0.0166,"Size_Height": 0.0225,"Lines": "2","Temperature_AMB": 70,"Temperature_MAX": 125,"Voltage_Insulation": 2000,"Assembling_Technology": "THT","VDE": ""},{"ID": 440477,"Series": "WE-FC","Size": "UT","Order_Code": "7448640417","Is_Internal": false,"Rated_Voltage": 250,"Inductance": 0.022,"Rated_Current": 0.4,"Resistance_DC": 1.635,"Size_Length": 0.0212,"Size_Width": 0.0166,"Size_Height": 0.0225,"Lines": "2","Temperature_AMB": 70,"Temperature_MAX": 125,"Voltage_Insulation": 2000,"Assembling_Technology": "THT","VDE": ""},{"ID": 440478,"Series": "WE-FC","Size": "UT","Order_Code": "7448640418","Is_Internal": false,"Rated_Voltage": 250,"Inductance": 0.033,"Rated_Current": 0.3,"Resistance_DC": 2.5,"Size_Length": 0.0212,"Size_Width": 0.0166,"Size_Height": 0.0225,"Lines": "2","Temperature_AMB": 70,"Temperature_MAX": 125,"Voltage_Insulation": 2000,"Assembling_Technology": "THT","VDE": ""},{"ID": 440479,"Series": "WE-FCL","Size": "ET35","Order_Code": "744866392","Is_Internal": false,"Rated_Voltage": 250,"Inductance": 0.0039,"Rated_Current": 5,"Resistance_DC": 0.05,"Size_Length": 0.037,"Size_Width": 0.026,"Size_Height": 0.045,"Lines": "2","Temperature_AMB": 70,"Temperature_MAX": 125,"Voltage_Insulation": 1500,"Assembling_Technology": "THT","VDE": ""},{"ID": 440480,"Series": "WE-FCL","Size": "ET35","Order_Code": "744866692","Is_Internal": false,"Rated_Voltage": 250,"Inductance": 0.0069,"Rated_Current": 4,"Resistance_DC": 0.068,"Size_Length": 0.037,"Size_Width": 0.026,"Size_Height": 0.045,"Lines": "2","Temperature_AMB": 70,"Temperature_MAX": 125,"Voltage_Insulation": 1500,"Assembling_Technology": "THT","VDE": ""},{"ID": 440481,"Series": "WE-FCL","Size": "ET35","Order_Code": "744866103","Is_Internal": false,"Rated_Voltage": 250,"Inductance": 0.01,"Rated_Current": 3.4,"Resistance_DC": 0.11,"Size_Length": 0.037,"Size_Width": 0.026,"Size_Height": 0.045,"Lines": "2","Temperature_AMB": 70,"Temperature_MAX": 125,"Voltage_Insulation": 1500,"Assembling_Technology": "THT","VDE": ""},{"ID": 440482,"Series": "WE-FCL","Size": "ET35","Order_Code": "744866223","Is_Internal": false,"Rated_Voltage": 250,"Inductance": 0.022,"Rated_Current": 2.5,"Resistance_DC": 0.2,"Size_Length": 0.037,"Size_Width": 0.026,"Size_Height": 0.045,"Lines": "2","Temperature_AMB": 70,"Temperature_MAX": 125,"Voltage_Insulation": 1500,"Assembling_Technology": "THT","VDE": ""},{"ID": 440483,"Series": "WE-FCL","Size": "ET35","Order_Code": "744866563","Is_Internal": false,"Rated_Voltage": 250,"Inductance": 0.056,"Rated_Current": 1.5,"Resistance_DC": 0.53,"Size_Length": 0.037,"Size_Width": 0.026,"Size_Height": 0.045,"Lines": "2","Temperature_AMB": 70,"Temperature_MAX": 125,"Voltage_Insulation": 1500,"Assembling_Technology": "THT","VDE": ""},{"ID": 440484,"Series": "WE-FCL","Size": "ET35","Order_Code": "744866104","Is_Internal": false,"Rated_Voltage": 250,"Inductance": 0.1,"Rated_Current": 1.25,"Resistance_DC": 0.9,"Size_Length": 0.037,"Size_Width": 0.026,"Size_Height": 0.045,"Lines": "2","Temperature_AMB": 70,"Temperature_MAX": 125,"Voltage_Insulation": 1500,"Assembling_Technology": "THT","VDE": ""},{"ID": 440485,"Series": "WE-CMBHV","Size": "XL","Order_Code": "744830007215","Is_Internal": false,"Rated_Voltage": 760,"Inductance": 0.0007,"Rated_Current": 21.5,"Resistance_DC": 0.0035,"Size_Length": 0.0425,"Size_Width": 0.023,"Size_Height": 0.0395,"Lines": "2","Temperature_AMB": 70,"Temperature_MAX": 125,"Voltage_Insulation": 3000,"Assembling_Technology": "","VDE": ""},{"ID": 440486,"Series": "WE-CMBHV","Size": "XL","Order_Code": "744830010185","Is_Internal": false,"Rated_Voltage": 760,"Inductance": 0.001,"Rated_Current": 18.5,"Resistance_DC": 0.0055,"Size_Length": 0.0415,"Size_Width": 0.023,"Size_Height": 0.0395,"Lines": "2","Temperature_AMB": 70,"Temperature_MAX": 125,"Voltage_Insulation": 3000,"Assembling_Technology": "","VDE": ""},{"ID": 440487,"Series": "WE-CMBHV","Size": "XL","Order_Code": "744830017132","Is_Internal": false,"Rated_Voltage": 760,"Inductance": 0.0017,"Rated_Current": 13.2,"Resistance_DC": 0.01,"Size_Length": 0.04,"Size_Width": 0.023,"Size_Height": 0.0395,"Lines": "2","Temperature_AMB": 70,"Temperature_MAX": 125,"Voltage_Insulation": 3000,"Assembling_Technology": "","VDE": ""},{"ID": 440488,"Series": "WE-CMBHV","Size": "XL","Order_Code": "744830025103","Is_Internal": false,"Rated_Voltage": 760,"Inductance": 0.0025,"Rated_Current": 10.3,"Resistance_DC": 0.018,"Size_Length": 0.0395,"Size_Width": 0.023,"Size_Height": 0.0395,"Lines": "2","Temperature_AMB": 70,"Temperature_MAX": 125,"Voltage_Insulation": 3000,"Assembling_Technology": "","VDE": ""},{"ID": 440489,"Series": "WE-CMBHV","Size": "XL","Order_Code": "744830039080","Is_Internal": false,"Rated_Voltage": 760,"Inductance": 0.0039,"Rated_Current": 8,"Resistance_DC": 0.031,"Size_Length": 0.0395,"Size_Width": 0.023,"Size_Height": 0.0395,"Lines": "2","Temperature_AMB": 70,"Temperature_MAX": 125,"Voltage_Insulation": 3000,"Assembling_Technology": "","VDE": ""},{"ID": 440490,"Series": "WE-CMBHV","Size": "XXL","Order_Code": "744831010205","Is_Internal": false,"Rated_Voltage": 760,"Inductance": 0.001,"Rated_Current": 20.5,"Resistance_DC": 0.0055,"Size_Length": 0.0465,"Size_Width": 0.028,"Size_Height": 0.0445,"Lines": "2","Temperature_AMB": 70,"Temperature_MAX": 125,"Voltage_Insulation": 3000,"Assembling_Technology": "","VDE": ""},{"ID": 440491,"Series": "WE-CMBHV","Size": "XXL","Order_Code": "744831016164","Is_Internal": false,"Rated_Voltage": 760,"Inductance": 0.0016,"Rated_Current": 16.4,"Resistance_DC": 0.0085,"Size_Length": 0.0465,"Size_Width": 0.028,"Size_Height": 0.0445,"Lines": "2","Temperature_AMB": 70,"Temperature_MAX": 125,"Voltage_Insulation": 3000,"Assembling_Technology": "","VDE": ""},{"ID": 440492,"Series": "WE-CMBHV","Size": "XXL","Order_Code": "744831020133","Is_Internal": false,"Rated_Voltage": 760,"Inductance": 0.002,"Rated_Current": 13.3,"Resistance_DC": 0.013,"Size_Length": 0.0455,"Size_Width": 0.028,"Size_Height": 0.0445,"Lines": "2","Temperature_AMB": 70,"Temperature_MAX": 125,"Voltage_Insulation": 3000,"Assembling_Technology": "","VDE": ""},{"ID": 440493,"Series": "WE-CMBHV","Size": "XXL","Order_Code": "744831034090","Is_Internal": false,"Rated_Voltage": 760,"Inductance": 0.0034,"Rated_Current": 9,"Resistance_DC": 0.027,"Size_Length": 0.0445,"Size_Width": 0.028,"Size_Height": 0.0445,"Lines": "2","Temperature_AMB": 70,"Temperature_MAX": 125,"Voltage_Insulation": 3000,"Assembling_Technology": "","VDE": ""},{"ID": 440494,"Series": "WE-CMBHV","Size": "XXL","Order_Code": "744831047068","Is_Internal": false,"Rated_Voltage": 760,"Inductance": 0.0047,"Rated_Current": 6.8,"Resistance_DC": 0.044,"Size_Length": 0.0445,"Size_Width": 0.028,"Size_Height": 0.0445,"Lines": "2","Temperature_AMB": 70,"Temperature_MAX": 125,"Voltage_Insulation": 3000,"Assembling_Technology": "","VDE": ""},{"ID": 440495,"Series": "WE-TPBHV","Size": "4XL","Order_Code": "744835021220","Is_Internal": false,"Rated_Voltage": 760,"Inductance": 0.0021,"Rated_Current": 22,"Resistance_DC": 0.009,"Size_Length": 0.07,"Size_Width": 0.07,"Size_Height": 0.039,"Lines": "3","Temperature_AMB": 85,"Temperature_MAX": 125,"Voltage_Insulation": 3000,"Assembling_Technology": "","VDE": ""},{"ID": 440496,"Series": "WE-TPBHV","Size": "4XL","Order_Code": "744835034160","Is_Internal": false,"Rated_Voltage": 760,"Inductance": 0.0034,"Rated_Current": 16,"Resistance_DC": 0.014,"Size_Length": 0.07,"Size_Width": 0.07,"Size_Height": 0.039,"Lines": "3","Temperature_AMB": 85,"Temperature_MAX": 125,"Voltage_Insulation": 3000,"Assembling_Technology": "","VDE": ""},{"ID": 440497,"Series": "WE-TPBHV","Size": "4XL","Order_Code": "744835050135","Is_Internal": false,"Rated_Voltage": 760,"Inductance": 0.005,"Rated_Current": 13.5,"Resistance_DC": 0.023,"Size_Length": 0.07,"Size_Width": 0.07,"Size_Height": 0.039,"Lines": "3","Temperature_AMB": 85,"Temperature_MAX": 125,"Voltage_Insulation": 3000,"Assembling_Technology": "","VDE": ""},{"ID": 440498,"Series": "WE-TPBHV","Size": "4XL","Order_Code": "744835090095","Is_Internal": false,"Rated_Voltage": 760,"Inductance": 0.009,"Rated_Current": 9.5,"Resistance_DC": 0.047,"Size_Length": 0.07,"Size_Width": 0.07,"Size_Height": 0.039,"Lines": "3","Temperature_AMB": 85,"Temperature_MAX": 125,"Voltage_Insulation": 3000,"Assembling_Technology": "","VDE": ""},{"ID": 440499,"Series": "WE-TPBHV","Size": "4XL","Order_Code": "744835150072","Is_Internal": false,"Rated_Voltage": 760,"Inductance": 0.015,"Rated_Current": 7.2,"Resistance_DC": 0.085,"Size_Length": 0.07,"Size_Width": 0.07,"Size_Height": 0.039,"Lines": "3","Temperature_AMB": 85,"Temperature_MAX": 125,"Voltage_Insulation": 3000,"Assembling_Technology": "","VDE": ""},{"ID": 440500,"Series": "WE-TPBHV","Size": "4XL","Order_Code": "744837002460","Is_Internal": false,"Rated_Voltage": 760,"Inductance": 0.0002,"Rated_Current": 46,"Resistance_DC": 0.0016,"Size_Length": 0.07,"Size_Width": 0.07,"Size_Height": 0.039,"Lines": "3","Temperature_AMB": 85,"Temperature_MAX": 125,"Voltage_Insulation": 3000,"Assembling_Technology": "","VDE": ""},{"ID": 440501,"Series": "WE-TPBHV","Size": "4XL","Order_Code": "744837006400","Is_Internal": false,"Rated_Voltage": 760,"Inductance": 0.0006,"Rated_Current": 40,"Resistance_DC": 0.0032,"Size_Length": 0.07,"Size_Width": 0.07,"Size_Height": 0.039,"Lines": "3","Temperature_AMB": 85,"Temperature_MAX": 125,"Voltage_Insulation": 3000,"Assembling_Technology": "","VDE": ""},{"ID": 440502,"Series": "WE-TPBHV","Size": "4XL","Order_Code": "744837010290","Is_Internal": false,"Rated_Voltage": 760,"Inductance": 0.001,"Rated_Current": 29,"Resistance_DC": 0.005,"Size_Length": 0.07,"Size_Width": 0.07,"Size_Height": 0.039,"Lines": "3","Temperature_AMB": 85,"Temperature_MAX": 125,"Voltage_Insulation": 3000,"Assembling_Technology": "","VDE": ""},{"ID": 440503,"Series": "WE-TPBHV","Size": "4XL","Order_Code": "744837018220","Is_Internal": false,"Rated_Voltage": 760,"Inductance": 0.0018,"Rated_Current": 22,"Resistance_DC": 0.009,"Size_Length": 0.07,"Size_Width": 0.07,"Size_Height": 0.039,"Lines": "3","Temperature_AMB": 85,"Temperature_MAX": 125,"Voltage_Insulation": 3000,"Assembling_Technology": "","VDE": ""},{"ID": 440504,"Series": "WE-TPBHV","Size": "4XL","Order_Code": "744838040400","Is_Internal": false,"Rated_Voltage": 760,"Inductance": 0.004,"Rated_Current": 40,"Resistance_DC": 0.0032,"Size_Length": 0.07,"Size_Width": 0.07,"Size_Height": 0.039,"Lines": "3","Temperature_AMB": 85,"Temperature_MAX": 125,"Voltage_Insulation": 3000,"Assembling_Technology": "","VDE": ""},{"ID": 440505,"Series": "WE-TPBHV","Size": "4XL","Order_Code": "744838180160","Is_Internal": false,"Rated_Voltage": 760,"Inductance": 0.018,"Rated_Current": 16,"Resistance_DC": 0.014,"Size_Length": 0.07,"Size_Width": 0.07,"Size_Height": 0.039,"Lines": "3","Temperature_AMB": 85,"Temperature_MAX": 125,"Voltage_Insulation": 3000,"Assembling_Technology": "","VDE": ""},{"ID": 440506,"Series": "WE-TPBHV","Size": "4XL","Order_Code": "744838480095","Is_Internal": false,"Rated_Voltage": 760,"Inductance": 0.048,"Rated_Current": 9.5,"Resistance_DC": 0.047,"Size_Length": 0.07,"Size_Width": 0.07,"Size_Height": 0.039,"Lines": "3","Temperature_AMB": 85,"Temperature_MAX": 125,"Voltage_Insulation": 3000,"Assembling_Technology": "","VDE": ""},{"ID": 440507,"Series": "WE-TPBHV","Size": "4XL","Order_Code": "744839003460","Is_Internal": false,"Rated_Voltage": 760,"Inductance": 0.003,"Rated_Current": 46,"Resistance_DC": 0.0016,"Size_Length": 0.07,"Size_Width": 0.07,"Size_Height": 0.039,"Lines": "3","Temperature_AMB": 85,"Temperature_MAX": 125,"Voltage_Insulation": 3000,"Assembling_Technology": "","VDE": ""},{"ID": 440508,"Series": "WE-TPBHV","Size": "4XL","Order_Code": "744839010400","Is_Internal": false,"Rated_Voltage": 760,"Inductance": 0.0105,"Rated_Current": 40,"Resistance_DC": 0.0032,"Size_Length": 0.07,"Size_Width": 0.07,"Size_Height": 0.039,"Lines": "3","Temperature_AMB": 85,"Temperature_MAX": 125,"Voltage_Insulation": 3000,"Assembling_Technology": "","VDE": ""},{"ID": 440509,"Series": "WE-TPBHV","Size": "4XL","Order_Code": "744839029220","Is_Internal": false,"Rated_Voltage": 760,"Inductance": 0.029,"Rated_Current": 22,"Resistance_DC": 0.009,"Size_Length": 0.07,"Size_Width": 0.07,"Size_Height": 0.039,"Lines": "3","Temperature_AMB": 85,"Temperature_MAX": 125,"Voltage_Insulation": 3000,"Assembling_Technology": "","VDE": ""},{"ID": 440510,"Series": "WE-TPBHV","Size": "4XL","Order_Code": "744839047160","Is_Internal": false,"Rated_Voltage": 760,"Inductance": 0.047,"Rated_Current": 16,"Resistance_DC": 0.014,"Size_Length": 0.07,"Size_Width": 0.07,"Size_Height": 0.039,"Lines": "3","Temperature_AMB": 85,"Temperature_MAX": 125,"Voltage_Insulation": 3000,"Assembling_Technology": "","VDE": ""},{"ID": 440511,"Series": "WE-TPBHV","Size": "4XL","Order_Code": "744839125095","Is_Internal": false,"Rated_Voltage": 760,"Inductance": 0.125,"Rated_Current": 9.5,"Resistance_DC": 0.047,"Size_Length": 0.07,"Size_Width": 0.07,"Size_Height": 0.039,"Lines": "3","Temperature_AMB": 85,"Temperature_MAX": 125,"Voltage_Insulation": 3000,"Assembling_Technology": "","VDE": ""},{"ID": 440512,"Series": "WE-TPBHV","Size": "4XL","Order_Code": "744839208072","Is_Internal": false,"Rated_Voltage": 760,"Inductance": 0.208,"Rated_Current": 7.2,"Resistance_DC": 0.085,"Size_Length": 0.07,"Size_Width": 0.07,"Size_Height": 0.039,"Lines": "3","Temperature_AMB": 85,"Temperature_MAX": 125,"Voltage_Insulation": 3000,"Assembling_Technology": "","VDE": ""},{"ID": 440513,"Series": "WE-LPCC","Size": "","Order_Code": "7448680100","Is_Internal": false,"Rated_Voltage": 250,"Inductance": 0.00045,"Rated_Current": 10,"Resistance_DC": 0.0096,"Size_Length": 0.025,"Size_Width": 0.0275,"Size_Height": 0.012,"Lines": "2","Temperature_AMB": 60,"Temperature_MAX": 115,"Voltage_Insulation": 1500,"Assembling_Technology": "THT","VDE": ""},{"ID": 440514,"Series": "WE-LPCC","Size": "","Order_Code": "7448680120","Is_Internal": false,"Rated_Voltage": 250,"Inductance": 0.00033,"Rated_Current": 12,"Resistance_DC": 0.006,"Size_Length": 0.025,"Size_Width": 0.0275,"Size_Height": 0.012,"Lines": "2","Temperature_AMB": 60,"Temperature_MAX": 115,"Voltage_Insulation": 1500,"Assembling_Technology": "THT","VDE": ""},{"ID": 440515,"Series": "WE-LPCC","Size": "","Order_Code": "7448680140","Is_Internal": false,"Rated_Voltage": 250,"Inductance": 0.00023,"Rated_Current": 16,"Resistance_DC": 0.0036,"Size_Length": 0.025,"Size_Width": 0.0275,"Size_Height": 0.012,"Lines": "2","Temperature_AMB": 60,"Temperature_MAX": 115,"Voltage_Insulation": 1500,"Assembling_Technology": "THT","VDE": ""},{"ID": 440516,"Series": "WE-LPCC","Size": "","Order_Code": "7448680180","Is_Internal": false,"Rated_Voltage": 250,"Inductance": 0.00015,"Rated_Current": 20,"Resistance_DC": 0.0019,"Size_Length": 0.025,"Size_Width": 0.0275,"Size_Height": 0.012,"Lines": "2","Temperature_AMB": 60,"Temperature_MAX": 115,"Voltage_Insulation": 1500,"Assembling_Technology": "THT","VDE": ""},{"ID": 440517,"Series": "WE-LPCC","Size": "","Order_Code": "7448680200","Is_Internal": false,"Rated_Voltage": 250,"Inductance": 0.00012,"Rated_Current": 23.5,"Resistance_DC": 0.0014,"Size_Length": 0.025,"Size_Width": 0.0275,"Size_Height": 0.012,"Lines": "2","Temperature_AMB": 60,"Temperature_MAX": 115,"Voltage_Insulation": 1500,"Assembling_Technology": "THT","VDE": ""},{"ID": 440518,"Series": "WE-TPB","Size": "3XL","Order_Code": "744833120060","Is_Internal": false,"Rated_Voltage": 500,"Inductance": 0.012,"Rated_Current": 6,"Resistance_DC": 0.065,"Size_Length": 0.047,"Size_Width": 0.047,"Size_Height": 0.039,"Lines": "3","Temperature_AMB": 60,"Temperature_MAX": 125,"Assembling_Technology": "THT","VDE": ""},{"ID": 440519,"Series": "WE-TPB","Size": "3XL","Order_Code": "744833084075","Is_Internal": false,"Rated_Voltage": 500,"Inductance": 0.0084,"Rated_Current": 7.5,"Resistance_DC": 0.05,"Size_Length": 0.047,"Size_Width": 0.047,"Size_Height": 0.039,"Lines": "3","Temperature_AMB": 60,"Temperature_MAX": 125,"Assembling_Technology": "THT","VDE": ""},{"ID": 440520,"Series": "WE-TPB","Size": "3XL","Order_Code": "744833052100","Is_Internal": false,"Rated_Voltage": 500,"Inductance": 0.0052,"Rated_Current": 10,"Resistance_DC": 0.027,"Size_Length": 0.047,"Size_Width": 0.047,"Size_Height": 0.039,"Lines": "3","Temperature_AMB": 60,"Temperature_MAX": 125,"Assembling_Technology": "THT","VDE": ""},{"ID": 440521,"Series": "WE-TPB","Size": "3XL","Order_Code": "744833027110","Is_Internal": false,"Rated_Voltage": 500,"Inductance": 0.0027,"Rated_Current": 11,"Resistance_DC": 0.018,"Size_Length": 0.047,"Size_Width": 0.047,"Size_Height": 0.039,"Lines": "3","Temperature_AMB": 60,"Temperature_MAX": 125,"Assembling_Technology": "THT","VDE": ""},{"ID": 440522,"Series": "WE-TPB","Size": "3XL","Order_Code": "744833011180","Is_Internal": false,"Rated_Voltage": 500,"Inductance": 0.0011,"Rated_Current": 18,"Resistance_DC": 0.007,"Size_Length": 0.047,"Size_Width": 0.047,"Size_Height": 0.039,"Lines": "3","Temperature_AMB": 60,"Temperature_MAX": 125,"Assembling_Technology": "THT","VDE": ""},{"ID": 440524,"Series": "WE-TPB","Size": "3XL","Order_Code": "744833005240","Is_Internal": false,"Rated_Voltage": 500,"Inductance": 0.00045,"Rated_Current": 24,"Resistance_DC": 0.003,"Size_Length": 0.047,"Size_Width": 0.047,"Size_Height": 0.039,"Lines": "3","Temperature_AMB": 60,"Temperature_MAX": 125,"Assembling_Technology": "THT","VDE": ""}], "Total": 240, "AggregateResults": "", "Error": "" }